{
  "totales": {
    "PorcentajeDesaparecidos": "0.00",
    "PorcentajeLocalizados": "100.00",
    "PorcentajeLocalizadosCV": "98.38",
    "PorcentajeLocalizadosSV": "1.62",
    "PorcentajeSoloDesaparecidos": "0.00",
    "PorcentajeSoloNoLocalizados": "0.00",
    "TotalDesaparecidos": "00",
    "TotalGlobal": "989",
    "TotalLocalizados": "989",
    "TotalLocalizadosCV": "973",
    "TotalLocalizadosSV": "16",
    "TotalSoloDesaparecidos": "00",
    "TotalSoloNoLocalizados": "00"
  },
  "espacial": {
    "Hombres": {
      "ACONCHI": 1,
      "AGUA PRIETA": 26,
      "ALAMOS": 1,
      "ALTAR": 0,
      "BENITO JUÁREZ": 1,
      "BENJAMÍN HILL": 0,
      "BÁCUM": 1,
      "CABORCA": 10,
      "CAJEME": 11,
      "CANANEA": 9,
      "CARBÓ": 0,
      "EMPALME": 4,
      "ETCHOJOA": 1,
      "GENERAL PLUTARCO ELÍAS CALLES": 1,
      "GUAYMAS": 10,
      "HERMOSILLO": 85,
      "HUATABAMPO": 2,
      "IMURIS": 0,
      "MAGDALENA": 4,
      "NACO": 1,
      "NACOZARI DE GARCÍA": 0,
      "NAVOJOA": 4,
      "NOGALES": 36,
      "PITIQUITO": 1,
      "PUERTO PEÑASCO": 17,
      "SAN LUIS RÍO COLORADO": 10,
      "SANTA ANA": 3,
      "SE DESCONOCE": 1,
      "SIN MUNICIPIO DE REFERENCIA": 4
    },
    "Indeterminado": {
      "ACONCHI": 0,
      "AGUA PRIETA": 0,
      "ALAMOS": 0,
      "ALTAR": 0,
      "BENITO JUÁREZ": 0,
      "BENJAMÍN HILL": 0,
      "BÁCUM": 0,
      "CABORCA": 0,
      "CAJEME": 0,
      "CANANEA": 0,
      "CARBÓ": 0,
      "EMPALME": 0,
      "ETCHOJOA": 0,
      "GENERAL PLUTARCO ELÍAS CALLES": 0,
      "GUAYMAS": 0,
      "HERMOSILLO": 0,
      "HUATABAMPO": 0,
      "IMURIS": 0,
      "MAGDALENA": 0,
      "NACO": 0,
      "NACOZARI DE GARCÍA": 0,
      "NAVOJOA": 0,
      "NOGALES": 0,
      "PITIQUITO": 0,
      "PUERTO PEÑASCO": 0,
      "SAN LUIS RÍO COLORADO": 0,
      "SANTA ANA": 0,
      "SE DESCONOCE": 0,
      "SIN MUNICIPIO DE REFERENCIA": 0
    },
    "Mujeres": {
      "ACONCHI": 0,
      "AGUA PRIETA": 116,
      "ALAMOS": 3,
      "ALTAR": 1,
      "BENITO JUÁREZ": 4,
      "BENJAMÍN HILL": 1,
      "BÁCUM": 3,
      "CABORCA": 19,
      "CAJEME": 68,
      "CANANEA": 20,
      "CARBÓ": 1,
      "EMPALME": 3,
      "ETCHOJOA": 3,
      "GENERAL PLUTARCO ELÍAS CALLES": 3,
      "GUAYMAS": 11,
      "HERMOSILLO": 220,
      "HUATABAMPO": 4,
      "IMURIS": 3,
      "MAGDALENA": 7,
      "NACO": 3,
      "NACOZARI DE GARCÍA": 4,
      "NAVOJOA": 9,
      "NOGALES": 132,
      "PITIQUITO": 0,
      "PUERTO PEÑASCO": 40,
      "SAN LUIS RÍO COLORADO": 56,
      "SANTA ANA": 3,
      "SE DESCONOCE": 1,
      "SIN MUNICIPIO DE REFERENCIA": 7
    }
  },
  "anual": {
    "Hombre": {
      "1.CIFRA SIN  AÑO DE REFERENCIA": 6,
      "1999": 0,
      "2003": 0,
      "2004": 0,
      "2005": 0,
      "2006": 1,
      "2007": 9,
      "2008": 5,
      "2009": 12,
      "2010": 15,
      "2011": 22,
      "2012": 30,
      "2013": 42,
      "2014": 14,
      "2015": 9,
      "2016": 18,
      "2017": 32,
      "2018": 5,
      "2019": 4,
      "2020": 8,
      "2021": 1,
      "2022": 3,
      "2023": 4,
      "2024": 4
    },
    "Indeterminado": {
      "1.CIFRA SIN  AÑO DE REFERENCIA": 0,
      "1999": 0,
      "2003": 0,
      "2004": 0,
      "2005": 0,
      "2006": 0,
      "2007": 0,
      "2008": 0,
      "2009": 0,
      "2010": 0,
      "2011": 0,
      "2012": 0,
      "2013": 0,
      "2014": 0,
      "2015": 0,
      "2016": 0,
      "2017": 0,
      "2018": 0,
      "2019": 0,
      "2020": 0,
      "2021": 0,
      "2022": 0,
      "2023": 0,
      "2024": 0
    },
    "Mujer": {
      "1.CIFRA SIN  AÑO DE REFERENCIA": 2,
      "1999": 1,
      "2003": 1,
      "2004": 3,
      "2005": 1,
      "2006": 6,
      "2007": 28,
      "2008": 27,
      "2009": 41,
      "2010": 39,
      "2011": 71,
      "2012": 118,
      "2013": 136,
      "2014": 47,
      "2015": 27,
      "2016": 63,
      "2017": 87,
      "2018": 8,
      "2019": 3,
      "2020": 10,
      "2021": 7,
      "2022": 10,
      "2023": 2,
      "2024": 7
    }
  },
  "mensual_ultimo_anio": {
    "Hombre": {
      "2022-AGOSTO": 1,
      "2022-JULIO": 0,
      "2022-JUNIO": 2,
      "2022-NOVIEMBRE": 0,
      "2023-AGOSTO": 1,
      "2023-ENERO": 1,
      "2023-MARZO": 1,
      "2023-SEPTIEMBRE": 1,
      "2024-ENERO": 1,
      "2024-JULIO": 0,
      "2024-JUNIO": 2,
      "2024-MARZO": 1
    },
    "Indeterminado": {
      "2022-AGOSTO": 0,
      "2022-JULIO": 0,
      "2022-JUNIO": 0,
      "2022-NOVIEMBRE": 0,
      "2023-AGOSTO": 0,
      "2023-ENERO": 0,
      "2023-MARZO": 0,
      "2023-SEPTIEMBRE": 0,
      "2024-ENERO": 0,
      "2024-JULIO": 0,
      "2024-JUNIO": 0,
      "2024-MARZO": 0
    },
    "Mujer": {
      "2022-AGOSTO": 1,
      "2022-JULIO": 1,
      "2022-JUNIO": 0,
      "2022-NOVIEMBRE": 3,
      "2023-AGOSTO": 1,
      "2023-ENERO": 0,
      "2023-MARZO": 1,
      "2023-SEPTIEMBRE": 0,
      "2024-ENERO": 0,
      "2024-JULIO": 3,
      "2024-JUNIO": 4,
      "2024-MARZO": 0
    }
  },
  "por_edad": {
    "Hombres": {
      "10": 7,
      "11": 3,
      "12": 10,
      "13": 28,
      "14": 31,
      "15": 35,
      "16": 32,
      "17": 42,
      "18": 32,
      "19": 24
    },
    "Indeterminado": {
      "10": 0,
      "11": 0,
      "12": 0,
      "13": 0,
      "14": 0,
      "15": 0,
      "16": 0,
      "17": 0,
      "18": 0,
      "19": 0
    },
    "Mujeres": {
      "10": 3,
      "11": 8,
      "12": 29,
      "13": 88,
      "14": 171,
      "15": 168,
      "16": 124,
      "17": 88,
      "18": 37,
      "19": 29
    }
  },
  "por_nacionalidad": {
    "Hombres": {
      "ESTADOUNIDENSE": 4,
      "GUATEMALTECA": 1,
      "HONDUREÑA": 1,
      "MEXICANA": 224,
      "SE DESCONOCE": 13,
      "SIN NACIONALIDAD DE REFERENCIA": 1
    },
    "Indeterminado": {
      "ESTADOUNIDENSE": 0,
      "GUATEMALTECA": 0,
      "HONDUREÑA": 0,
      "MEXICANA": 0,
      "SE DESCONOCE": 0,
      "SIN NACIONALIDAD DE REFERENCIA": 0
    },
    "Mujeres": {
      "ESTADOUNIDENSE": 20,
      "GUATEMALTECA": 0,
      "HONDUREÑA": 0,
      "MEXICANA": 708,
      "SE DESCONOCE": 12,
      "SIN NACIONALIDAD DE REFERENCIA": 5
    }
  },
  "parametros": {
    "titulo": "PERSONAS LOCALIZADAS",
    "id_estatus_victima": "6",
    "fecha_inicio": "",
    "fecha_fin": "",
    "id_estado": "26",
    "id_municipio": "0",
    "mostrar_fecha_nula": "0",
    "id_colonia": "0",
    "id_nacionalidad": "0",
    "edad_inicio": "10",
    "edad_fin": "19",
    "mostrar_edad_nula": "0",
    "id_hipotesis": "",
    "id_medio_conocimiento": "",
    "id_circunstancia": "",
    "tiene_discapacidad": "",
    "id_tipo_discapacidad": "0",
    "id_etnia": "0",
    "id_lengua": "0",
    "id_religion": "",
    "es_migrante": "",
    "id_estatus_migratorio": "0",
    "es_lgbttti": "",
    "es_servidor_publico": "",
    "es_defensor_dh": "",
    "es_periodista": "",
    "es_sindicalista": "",
    "es_ong": "",
    "id_hipotesis_no_localizacion": "0",
    "id_delito": "0"
  }
}