{
  "totales": {
    "PorcentajeDesaparecidos": "26.57",
    "PorcentajeLocalizados": "73.43",
    "PorcentajeLocalizadosCV": "98.10",
    "PorcentajeLocalizadosSV": "1.90",
    "PorcentajeSoloDesaparecidos": "85.09",
    "PorcentajeSoloNoLocalizados": "14.91",
    "TotalDesaparecidos": "228",
    "TotalGlobal": "858",
    "TotalLocalizados": "630",
    "TotalLocalizadosCV": "618",
    "TotalLocalizadosSV": "12",
    "TotalSoloDesaparecidos": "194",
    "TotalSoloNoLocalizados": "34"
  },
  "espacial": {
    "Hombres": {
      "ACAPONETA": 1,
      "AHUACATLÁN": 2,
      "AMATLÁN DE CAÑAS": 1,
      "BAHÍA DE BANDERAS": 42,
      "COMPOSTELA": 10,
      "DEL NAYAR": 4,
      "HUAJICORI": 3,
      "IXTLÁN DEL RÍO": 3,
      "JALA": 3,
      "LA YESCA": 2,
      "ROSAMORADA": 6,
      "RUÍZ": 2,
      "SAN BLAS": 3,
      "SAN PEDRO LAGUNILLAS": 0,
      "SANTA MARÍA DEL ORO": 0,
      "SANTIAGO IXCUINTLA": 7,
      "SE DESCONOCE": 0,
      "SIN MUNICIPIO DE REFERENCIA": 17,
      "TECUALA": 5,
      "TEPIC": 157,
      "TUXPAN": 10,
      "XALISCO": 8
    },
    "Indeterminado": {
      "ACAPONETA": 0,
      "AHUACATLÁN": 0,
      "AMATLÁN DE CAÑAS": 0,
      "BAHÍA DE BANDERAS": 0,
      "COMPOSTELA": 0,
      "DEL NAYAR": 0,
      "HUAJICORI": 0,
      "IXTLÁN DEL RÍO": 0,
      "JALA": 0,
      "LA YESCA": 0,
      "ROSAMORADA": 0,
      "RUÍZ": 0,
      "SAN BLAS": 0,
      "SAN PEDRO LAGUNILLAS": 0,
      "SANTA MARÍA DEL ORO": 0,
      "SANTIAGO IXCUINTLA": 0,
      "SE DESCONOCE": 1,
      "SIN MUNICIPIO DE REFERENCIA": 0,
      "TECUALA": 0,
      "TEPIC": 0,
      "TUXPAN": 0,
      "XALISCO": 0
    },
    "Mujeres": {
      "ACAPONETA": 10,
      "AHUACATLÁN": 4,
      "AMATLÁN DE CAÑAS": 0,
      "BAHÍA DE BANDERAS": 68,
      "COMPOSTELA": 22,
      "DEL NAYAR": 14,
      "HUAJICORI": 4,
      "IXTLÁN DEL RÍO": 4,
      "JALA": 2,
      "LA YESCA": 3,
      "ROSAMORADA": 17,
      "RUÍZ": 8,
      "SAN BLAS": 9,
      "SAN PEDRO LAGUNILLAS": 2,
      "SANTA MARÍA DEL ORO": 5,
      "SANTIAGO IXCUINTLA": 37,
      "SE DESCONOCE": 6,
      "SIN MUNICIPIO DE REFERENCIA": 13,
      "TECUALA": 17,
      "TEPIC": 295,
      "TUXPAN": 13,
      "XALISCO": 18
    }
  },
  "anual": {
    "Hombre": {
      "1.CIFRA SIN  AÑO DE REFERENCIA": 34,
      "1981": 1,
      "1993": 1,
      "2005": 0,
      "2006": 1,
      "2008": 1,
      "2009": 1,
      "2010": 2,
      "2011": 2,
      "2012": 0,
      "2014": 1,
      "2015": 0,
      "2017": 13,
      "2018": 8,
      "2019": 17,
      "2020": 26,
      "2021": 30,
      "2022": 47,
      "2023": 68,
      "2024": 33
    },
    "Indeterminado": {
      "1.CIFRA SIN  AÑO DE REFERENCIA": 1,
      "1981": 0,
      "1993": 0,
      "2005": 0,
      "2006": 0,
      "2008": 0,
      "2009": 0,
      "2010": 0,
      "2011": 0,
      "2012": 0,
      "2014": 0,
      "2015": 0,
      "2017": 0,
      "2018": 0,
      "2019": 0,
      "2020": 0,
      "2021": 0,
      "2022": 0,
      "2023": 0,
      "2024": 0
    },
    "Mujer": {
      "1.CIFRA SIN  AÑO DE REFERENCIA": 64,
      "1981": 0,
      "1993": 0,
      "2005": 1,
      "2006": 0,
      "2008": 0,
      "2009": 0,
      "2010": 1,
      "2011": 0,
      "2012": 3,
      "2014": 4,
      "2015": 1,
      "2017": 6,
      "2018": 13,
      "2019": 24,
      "2020": 61,
      "2021": 118,
      "2022": 81,
      "2023": 117,
      "2024": 77
    }
  },
  "mensual_ultimo_anio": {
    "Hombre": {
      "2023-AGOSTO": 3,
      "2023-DICIEMBRE": 3,
      "2023-NOVIEMBRE": 9,
      "2023-OCTUBRE": 3,
      "2023-SEPTIEMBRE": 8,
      "2024-ABRIL": 3,
      "2024-ENERO": 4,
      "2024-FEBRERO": 9,
      "2024-JULIO": 4,
      "2024-JUNIO": 3,
      "2024-MARZO": 5,
      "2024-MAYO": 5
    },
    "Indeterminado": {
      "2023-AGOSTO": 0,
      "2023-DICIEMBRE": 0,
      "2023-NOVIEMBRE": 0,
      "2023-OCTUBRE": 0,
      "2023-SEPTIEMBRE": 0,
      "2024-ABRIL": 0,
      "2024-ENERO": 0,
      "2024-FEBRERO": 0,
      "2024-JULIO": 0,
      "2024-JUNIO": 0,
      "2024-MARZO": 0,
      "2024-MAYO": 0
    },
    "Mujer": {
      "2023-AGOSTO": 14,
      "2023-DICIEMBRE": 8,
      "2023-NOVIEMBRE": 13,
      "2023-OCTUBRE": 7,
      "2023-SEPTIEMBRE": 5,
      "2024-ABRIL": 12,
      "2024-ENERO": 12,
      "2024-FEBRERO": 13,
      "2024-JULIO": 12,
      "2024-JUNIO": 8,
      "2024-MARZO": 11,
      "2024-MAYO": 9
    }
  },
  "por_edad": {
    "Hombres": {
      "10": 11,
      "11": 11,
      "12": 16,
      "13": 17,
      "14": 22,
      "15": 39,
      "16": 40,
      "17": 47,
      "18": 39,
      "19": 44
    },
    "Indeterminado": {
      "10": 0,
      "11": 0,
      "12": 0,
      "13": 0,
      "14": 0,
      "15": 1,
      "16": 0,
      "17": 0,
      "18": 0,
      "19": 0
    },
    "Mujeres": {
      "10": 8,
      "11": 7,
      "12": 26,
      "13": 54,
      "14": 87,
      "15": 105,
      "16": 102,
      "17": 89,
      "18": 57,
      "19": 36
    }
  },
  "por_nacionalidad": {
    "Hombres": {
      "ESTADOUNIDENSE": 0,
      "MARROQUI": 0,
      "MEXICANA": 280,
      "NICARAGUENSE": 0,
      "SE DESCONOCE": 6,
      "SIN NACIONALIDAD DE REFERENCIA": 0
    },
    "Indeterminado": {
      "ESTADOUNIDENSE": 0,
      "MARROQUI": 0,
      "MEXICANA": 0,
      "NICARAGUENSE": 0,
      "SE DESCONOCE": 1,
      "SIN NACIONALIDAD DE REFERENCIA": 0
    },
    "Mujeres": {
      "ESTADOUNIDENSE": 7,
      "MARROQUI": 2,
      "MEXICANA": 554,
      "NICARAGUENSE": 1,
      "SE DESCONOCE": 6,
      "SIN NACIONALIDAD DE REFERENCIA": 1
    }
  },
  "parametros": {
    "titulo": "PERSONAS DESAPARECIDAS, NO LOCALIZADAS Y LOCALIZADAS",
    "id_estatus_victima": "0",
    "fecha_inicio": "",
    "fecha_fin": "",
    "id_estado": "18",
    "id_municipio": "0",
    "mostrar_fecha_nula": "0",
    "id_colonia": "0",
    "id_nacionalidad": "0",
    "edad_inicio": "10",
    "edad_fin": "19",
    "mostrar_edad_nula": "0",
    "id_hipotesis": "",
    "id_medio_conocimiento": "",
    "id_circunstancia": "",
    "tiene_discapacidad": "",
    "id_tipo_discapacidad": "0",
    "id_etnia": "0",
    "id_lengua": "0",
    "id_religion": "",
    "es_migrante": "",
    "id_estatus_migratorio": "0",
    "es_lgbttti": "",
    "es_servidor_publico": "",
    "es_defensor_dh": "",
    "es_periodista": "",
    "es_sindicalista": "",
    "es_ong": "",
    "id_hipotesis_no_localizacion": "0",
    "id_delito": "0"
  }
}