{
  "totales": {
    "PorcentajeDesaparecidos": "100.00",
    "PorcentajeLocalizados": "0.00",
    "PorcentajeLocalizadosCV": "0.00",
    "PorcentajeLocalizadosSV": "0.00",
    "PorcentajeSoloDesaparecidos": "100.00",
    "PorcentajeSoloNoLocalizados": "0.00",
    "TotalDesaparecidos": "139",
    "TotalGlobal": "139",
    "TotalLocalizados": "00",
    "TotalLocalizadosCV": "00",
    "TotalLocalizadosSV": "00",
    "TotalSoloDesaparecidos": "139",
    "TotalSoloNoLocalizados": "00"
  },
  "espacial": {
    "Hombres": {
      "ACAPETAHUA": 0,
      "ALTAMIRANO": 1,
      "AMATENANGO DE LA FRONTERA": 1,
      "ANGEL ALBINO CORZO": 0,
      "ARRIAGA": 5,
      "BELLA VISTA": 0,
      "BENEMÉRITO DE LAS AMÉRICAS": 1,
      "BERRIOZÁBAL": 1,
      "BOCHIL": 0,
      "CATAZAJÁ": 1,
      "CHANAL": 1,
      "CHENALHÓ": 1,
      "CHIAPA DE CORZO": 2,
      "CHICOMUSELO": 0,
      "CHILÓN": 0,
      "CINTALAPA": 0,
      "COMITÁN DE DOMÍNGUEZ": 4,
      "COPAINALÁ": 0,
      "ESCUINTLA": 2,
      "FRONTERA COMALAPA": 1,
      "HUEHUETÁN": 2,
      "HUIXTLA": 1,
      "LA CONCORDIA": 3,
      "LA GRANDEZA": 1,
      "MAPASTEPEC": 0,
      "MARQUÉS DE COMILLAS": 0,
      "OCOSINGO": 1,
      "OCOZOCOAUTLA DE ESPINOSA": 1,
      "PALENQUE": 3,
      "PICHUCALCO": 0,
      "PIJIJIAPAN": 1,
      "PUEBLO NUEVO SOLISTAHUACÁN": 0,
      "REFORMA": 1,
      "SAN CRISTÓBAL DE LAS CASAS": 2,
      "SE DESCONOCE": 4,
      "SILTEPEC": 1,
      "SIN MUNICIPIO DE REFERENCIA": 0,
      "SUCHIATE": 1,
      "TAPACHULA": 11,
      "TAPILULA": 1,
      "TECPATÁN": 0,
      "TEOPISCA": 1,
      "TILA": 1,
      "TUMBALÁ": 1,
      "TUXTLA GUTIÉRREZ": 8,
      "UNIÓN JUÁREZ": 0,
      "VENUSTIANO CARRANZA": 1,
      "VILLA COMALTITLÁN": 1,
      "VILLAFLORES": 1,
      "YAJALÓN": 2
    },
    "Indeterminado": {
      "ACAPETAHUA": 0,
      "ALTAMIRANO": 0,
      "AMATENANGO DE LA FRONTERA": 0,
      "ANGEL ALBINO CORZO": 0,
      "ARRIAGA": 0,
      "BELLA VISTA": 0,
      "BENEMÉRITO DE LAS AMÉRICAS": 0,
      "BERRIOZÁBAL": 0,
      "BOCHIL": 0,
      "CATAZAJÁ": 0,
      "CHANAL": 0,
      "CHENALHÓ": 0,
      "CHIAPA DE CORZO": 0,
      "CHICOMUSELO": 0,
      "CHILÓN": 0,
      "CINTALAPA": 0,
      "COMITÁN DE DOMÍNGUEZ": 0,
      "COPAINALÁ": 0,
      "ESCUINTLA": 0,
      "FRONTERA COMALAPA": 0,
      "HUEHUETÁN": 0,
      "HUIXTLA": 0,
      "LA CONCORDIA": 0,
      "LA GRANDEZA": 0,
      "MAPASTEPEC": 0,
      "MARQUÉS DE COMILLAS": 0,
      "OCOSINGO": 0,
      "OCOZOCOAUTLA DE ESPINOSA": 0,
      "PALENQUE": 0,
      "PICHUCALCO": 0,
      "PIJIJIAPAN": 0,
      "PUEBLO NUEVO SOLISTAHUACÁN": 0,
      "REFORMA": 0,
      "SAN CRISTÓBAL DE LAS CASAS": 0,
      "SE DESCONOCE": 0,
      "SILTEPEC": 0,
      "SIN MUNICIPIO DE REFERENCIA": 0,
      "SUCHIATE": 0,
      "TAPACHULA": 0,
      "TAPILULA": 0,
      "TECPATÁN": 0,
      "TEOPISCA": 0,
      "TILA": 0,
      "TUMBALÁ": 0,
      "TUXTLA GUTIÉRREZ": 0,
      "UNIÓN JUÁREZ": 0,
      "VENUSTIANO CARRANZA": 0,
      "VILLA COMALTITLÁN": 0,
      "VILLAFLORES": 0,
      "YAJALÓN": 0
    },
    "Mujeres": {
      "ACAPETAHUA": 1,
      "ALTAMIRANO": 0,
      "AMATENANGO DE LA FRONTERA": 0,
      "ANGEL ALBINO CORZO": 1,
      "ARRIAGA": 2,
      "BELLA VISTA": 1,
      "BENEMÉRITO DE LAS AMÉRICAS": 0,
      "BERRIOZÁBAL": 0,
      "BOCHIL": 1,
      "CATAZAJÁ": 3,
      "CHANAL": 0,
      "CHENALHÓ": 0,
      "CHIAPA DE CORZO": 1,
      "CHICOMUSELO": 1,
      "CHILÓN": 1,
      "CINTALAPA": 2,
      "COMITÁN DE DOMÍNGUEZ": 5,
      "COPAINALÁ": 1,
      "ESCUINTLA": 1,
      "FRONTERA COMALAPA": 4,
      "HUEHUETÁN": 0,
      "HUIXTLA": 1,
      "LA CONCORDIA": 0,
      "LA GRANDEZA": 0,
      "MAPASTEPEC": 3,
      "MARQUÉS DE COMILLAS": 1,
      "OCOSINGO": 3,
      "OCOZOCOAUTLA DE ESPINOSA": 0,
      "PALENQUE": 4,
      "PICHUCALCO": 3,
      "PIJIJIAPAN": 0,
      "PUEBLO NUEVO SOLISTAHUACÁN": 1,
      "REFORMA": 5,
      "SAN CRISTÓBAL DE LAS CASAS": 0,
      "SE DESCONOCE": 4,
      "SILTEPEC": 0,
      "SIN MUNICIPIO DE REFERENCIA": 2,
      "SUCHIATE": 1,
      "TAPACHULA": 6,
      "TAPILULA": 0,
      "TECPATÁN": 1,
      "TEOPISCA": 0,
      "TILA": 0,
      "TUMBALÁ": 1,
      "TUXTLA GUTIÉRREZ": 5,
      "UNIÓN JUÁREZ": 1,
      "VENUSTIANO CARRANZA": 0,
      "VILLA COMALTITLÁN": 1,
      "VILLAFLORES": 0,
      "YAJALÓN": 0
    }
  },
  "anual": {
    "Hombre": {
      "1.CIFRA SIN  AÑO DE REFERENCIA": 0,
      "1994": 1,
      "2002": 0,
      "2006": 1,
      "2011": 0,
      "2012": 1,
      "2013": 0,
      "2015": 3,
      "2016": 1,
      "2017": 0,
      "2018": 7,
      "2020": 6,
      "2021": 1,
      "2022": 2,
      "2023": 24,
      "2024": 24
    },
    "Indeterminado": {
      "1.CIFRA SIN  AÑO DE REFERENCIA": 0,
      "1994": 0,
      "2002": 0,
      "2006": 0,
      "2011": 0,
      "2012": 0,
      "2013": 0,
      "2015": 0,
      "2016": 0,
      "2017": 0,
      "2018": 0,
      "2020": 0,
      "2021": 0,
      "2022": 0,
      "2023": 0,
      "2024": 0
    },
    "Mujer": {
      "1.CIFRA SIN  AÑO DE REFERENCIA": 3,
      "1994": 0,
      "2002": 1,
      "2006": 1,
      "2011": 1,
      "2012": 0,
      "2013": 2,
      "2015": 2,
      "2016": 5,
      "2017": 3,
      "2018": 2,
      "2020": 5,
      "2021": 0,
      "2022": 5,
      "2023": 14,
      "2024": 24
    }
  },
  "mensual_ultimo_anio": {
    "Hombre": {
      "2023-AGOSTO": 2,
      "2023-DICIEMBRE": 1,
      "2023-NOVIEMBRE": 5,
      "2023-OCTUBRE": 5,
      "2023-SEPTIEMBRE": 4,
      "2024-ABRIL": 5,
      "2024-ENERO": 2,
      "2024-FEBRERO": 3,
      "2024-JULIO": 6,
      "2024-JUNIO": 6,
      "2024-MARZO": 1,
      "2024-MAYO": 1
    },
    "Indeterminado": {
      "2023-AGOSTO": 0,
      "2023-DICIEMBRE": 0,
      "2023-NOVIEMBRE": 0,
      "2023-OCTUBRE": 0,
      "2023-SEPTIEMBRE": 0,
      "2024-ABRIL": 0,
      "2024-ENERO": 0,
      "2024-FEBRERO": 0,
      "2024-JULIO": 0,
      "2024-JUNIO": 0,
      "2024-MARZO": 0,
      "2024-MAYO": 0
    },
    "Mujer": {
      "2023-AGOSTO": 0,
      "2023-DICIEMBRE": 1,
      "2023-NOVIEMBRE": 2,
      "2023-OCTUBRE": 1,
      "2023-SEPTIEMBRE": 4,
      "2024-ABRIL": 4,
      "2024-ENERO": 0,
      "2024-FEBRERO": 5,
      "2024-JULIO": 3,
      "2024-JUNIO": 7,
      "2024-MARZO": 2,
      "2024-MAYO": 3
    }
  },
  "por_edad": {
    "Hombres": {
      "10": 5,
      "11": 2,
      "12": 1,
      "13": 2,
      "14": 7,
      "15": 6,
      "16": 9,
      "17": 12,
      "18": 13,
      "19": 14
    },
    "Indeterminado": {
      "10": 0,
      "11": 0,
      "12": 0,
      "13": 0,
      "14": 0,
      "15": 0,
      "16": 0,
      "17": 0,
      "18": 0,
      "19": 0
    },
    "Mujeres": {
      "10": 3,
      "11": 4,
      "12": 6,
      "13": 8,
      "14": 8,
      "15": 13,
      "16": 11,
      "17": 7,
      "18": 6,
      "19": 2
    }
  },
  "por_nacionalidad": {
    "Hombres": {
      "COLOMBIANA": 1,
      "CUBANA": 1,
      "ECUATORIANA": 1,
      "ESTADOUNIDENSE": 1,
      "GUATEMALTECA": 8,
      "HONDUREÑA": 3,
      "MEXICANA": 54,
      "NICARAGUENSE": 0,
      "SALVADORENA": 1,
      "SIN NACIONALIDAD DE REFERENCIA": 1
    },
    "Indeterminado": {
      "COLOMBIANA": 0,
      "CUBANA": 0,
      "ECUATORIANA": 0,
      "ESTADOUNIDENSE": 0,
      "GUATEMALTECA": 0,
      "HONDUREÑA": 0,
      "MEXICANA": 0,
      "NICARAGUENSE": 0,
      "SALVADORENA": 0,
      "SIN NACIONALIDAD DE REFERENCIA": 0
    },
    "Mujeres": {
      "COLOMBIANA": 0,
      "CUBANA": 1,
      "ECUATORIANA": 0,
      "ESTADOUNIDENSE": 1,
      "GUATEMALTECA": 3,
      "HONDUREÑA": 4,
      "MEXICANA": 57,
      "NICARAGUENSE": 1,
      "SALVADORENA": 0,
      "SIN NACIONALIDAD DE REFERENCIA": 1
    }
  },
  "parametros": {
    "titulo": "PERSONAS DESAPARECIDAS",
    "id_estatus_victima": "4",
    "fecha_inicio": "",
    "fecha_fin": "",
    "id_estado": "7",
    "id_municipio": "0",
    "mostrar_fecha_nula": "0",
    "id_colonia": "0",
    "id_nacionalidad": "0",
    "edad_inicio": "10",
    "edad_fin": "19",
    "mostrar_edad_nula": "0",
    "id_hipotesis": "",
    "id_medio_conocimiento": "",
    "id_circunstancia": "",
    "tiene_discapacidad": "",
    "id_tipo_discapacidad": "0",
    "id_etnia": "0",
    "id_lengua": "0",
    "id_religion": "",
    "es_migrante": "",
    "id_estatus_migratorio": "0",
    "es_lgbttti": "",
    "es_servidor_publico": "",
    "es_defensor_dh": "",
    "es_periodista": "",
    "es_sindicalista": "",
    "es_ong": "",
    "id_hipotesis_no_localizacion": "0",
    "id_delito": "0"
  }
}