{
  "totales": {
    "PorcentajeDesaparecidos": "17.93",
    "PorcentajeLocalizados": "82.07",
    "PorcentajeLocalizadosCV": "97.48",
    "PorcentajeLocalizadosSV": "2.52",
    "PorcentajeSoloDesaparecidos": "80.83",
    "PorcentajeSoloNoLocalizados": "19.17",
    "TotalDesaparecidos": "746",
    "TotalGlobal": "4161",
    "TotalLocalizados": "3415",
    "TotalLocalizadosCV": "3329",
    "TotalLocalizadosSV": "86",
    "TotalSoloDesaparecidos": "603",
    "TotalSoloNoLocalizados": "143"
  },
  "espacial": {
    "Hombres": {
      "ABEJONES": 3,
      "ACATLÁN DE PÉREZ FIGUEROA": 2,
      "AGUA PRIETA": 0,
      "ANIMAS TRUJANO": 14,
      "ASUNCIÓN IXTALTEPEC": 1,
      "ASUNCIÓN NOCHIXTLÁN": 1,
      "ASUNCIÓN TLACOLULITA": 1,
      "AYOQUEZCO DE ALDAMA": 1,
      "CAPULÁLPAM DE MÉNDEZ": 1,
      "CHAHUITES": 1,
      "CHALCATONGO DE HIDALGO": 0,
      "CIUDAD IXTEPEC": 5,
      "COATECAS ALTAS": 2,
      "CONCEPCIÓN PÁPALO": 1,
      "CONSTANCIA DEL ROSARIO": 0,
      "COSOLAPA": 6,
      "COXCATLÁN": 1,
      "CUILÁPAM DE GUERRERO": 31,
      "EL ESPINAL": 0,
      "ELOXOCHITLÁN DE FLORES MAGÓN": 1,
      "GUADALUPE DE RAMÍREZ": 1,
      "GUELATAO DE JUÁREZ": 0,
      "GUEVEA DE HUMBOLDT": 1,
      "HEROICA CIUDAD DE EJUTLA DE CRESPO": 5,
      "HEROICA CIUDAD DE TLAXIACO": 4,
      "HUAJUAPAN DE LEÓN": 9,
      "HUAUTLA DE JIMÉNEZ": 5,
      "IXTLÁN DE JUÁREZ": 1,
      "JUCHITÁN DE ZARAGOZA": 9,
      "LA REFORMA": 2,
      "LOMA BONITA": 11,
      "MAGDALENA APASCO": 4,
      "MAGDALENA JALTEPEC": 1,
      "MAGDALENA MIXTEPEC": 0,
      "MAGDALENA OCOTLÁN": 1,
      "MATÍAS ROMERO AVENDAÑO": 1,
      "MAZATLÁN VILLA DE FLORES": 2,
      "MESONES HIDALGO": 1,
      "MIAHUATLÁN DE PORFIRIO DÍAZ": 6,
      "NAZARENO ETLA": 1,
      "OAXACA DE JUÁREZ": 723,
      "OCOTLÁN DE MORELOS": 9,
      "PINOTEPA DE DON LUIS": 1,
      "PLUMA HIDALGO": 0,
      "PUTLA VILLA DE GUERRERO": 8,
      "REYES ETLA": 0,
      "SALINA CRUZ": 10,
      "SAN AGUSTÍN ATENANGO": 7,
      "SAN AGUSTÍN DE LAS JUNTAS": 24,
      "SAN AGUSTÍN ETLA": 2,
      "SAN AGUSTÍN YATARENI": 5,
      "SAN ANDRÉS HUAYAPAM": 6,
      "SAN ANDRÉS IXTLAHUACA": 4,
      "SAN ANDRÉS ZAUTLA": 3,
      "SAN ANTONINO CASTILLO VELASCO": 0,
      "SAN ANTONINO EL ALTO": 1,
      "SAN ANTONIO DE LA CAL": 43,
      "SAN ANTONIO HUITEPEC": 1,
      "SAN BALTAZAR YATZACHI EL BAJO": 1,
      "SAN BARTOLO COYOTEPEC": 33,
      "SAN BERNARDO MIXTEPEC": 1,
      "SAN CRISTÓBAL AMATLÁN": 3,
      "SAN CRISTÓBAL LACHIRIOAG": 2,
      "SAN DIONISIO OCOTEPEC": 1,
      "SAN ESTEBAN ATATLAHUCA": 4,
      "SAN FELIPE JALAPA DE DÍAZ": 3,
      "SAN FELIPE USILA": 0,
      "SAN FRANCISCO IXHUATÁN": 2,
      "SAN FRANCISCO LACHIGOLÓ": 4,
      "SAN FRANCISCO TELIXTLAHUACA": 2,
      "SAN ILDEFONSO AMATLÁN": 1,
      "SAN ILDEFONSO VILLA ALTA": 1,
      "SAN JACINTO AMILPAS": 31,
      "SAN JERÓNIMO TAVICHE": 1,
      "SAN JOSÉ DEL PROGRESO": 1,
      "SAN JOSÉ LACHIGUIRI": 0,
      "SAN JOSÉ TENANGO": 0,
      "SAN JUAN BAUTISTA CUICATLÁN": 3,
      "SAN JUAN BAUTISTA GUELACHE": 1,
      "SAN JUAN BAUTISTA TUXTEPEC": 38,
      "SAN JUAN BAUTISTA VALLE NACIONAL": 3,
      "SAN JUAN COTZOCÓN": 6,
      "SAN JUAN GUELAVÍA": 0,
      "SAN JUAN GUICHICOVI": 0,
      "SAN JUAN JUQUILA MIXES": 1,
      "SAN JUAN JUQUILA VIJANOS": 1,
      "SAN JUAN LALANA": 1,
      "SAN JUAN MAZATLÁN": 1,
      "SAN JUAN MIXTEPEC JUXTLAHUACA": 2,
      "SAN JUAN QUIAHIJE": 1,
      "SAN JUAN TAMAZOLA": 0,
      "SAN JUAN TEITIPAC": 1,
      "SAN LORENZO CACAOTEPEC": 7,
      "SAN LORENZO TEXMELUCAN": 1,
      "SAN LUCAS OJITLÁN": 1,
      "SAN LUIS AMATLÁN": 0,
      "SAN MARTÍN TILCAJETE": 2,
      "SAN MATEO PEÑASCO": 0,
      "SAN MIGUEL CHICAHUA": 2,
      "SAN MIGUEL HUAUTLA": 0,
      "SAN MIGUEL MIXTEPEC": 0,
      "SAN MIGUEL QUETZALTEPEC": 1,
      "SAN MIGUEL SOYALTEPEC": 2,
      "SAN PABLO COATLÁN": 1,
      "SAN PABLO ETLA": 8,
      "SAN PABLO HUITZO": 2,
      "SAN PABLO HUIXTEPEC": 5,
      "SAN PABLO VILLA DE MITLA": 1,
      "SAN PEDRO CAJONOS": 0,
      "SAN PEDRO IXTLAHUACA": 20,
      "SAN PEDRO JOCOTIPAC": 1,
      "SAN PEDRO MIXTEPEC-JUQUILA": 4,
      "SAN PEDRO OCOTEPEC": 0,
      "SAN PEDRO POCHUTLA": 5,
      "SAN PEDRO TAPANATEPEC": 3,
      "SAN PEDRO TOTOLAPA": 4,
      "SAN PEDRO Y SAN PABLO AYUTLA": 2,
      "SAN PEDRO Y SAN PABLO TEPOSCOLULA": 1,
      "SAN PEDRO YANERI": 1,
      "SAN RAYMUNDO JALPAN": 2,
      "SAN SEBASTIÁN NICANANDUTA": 1,
      "SAN SEBASTIÁN TECOMAXTLAHUACA": 1,
      "SAN SEBASTIÁN TEITIPAC": 0,
      "SAN SEBASTIÁN TUTLA": 14,
      "SAN VICENTE COATLÁN": 1,
      "SANTA CATARINA JUQUILA": 0,
      "SANTA CATARINA MINAS": 1,
      "SANTA CATARINA QUIANÉ": 2,
      "SANTA CATARINA TAYATA": 0,
      "SANTA CRUZ AMILPAS": 10,
      "SANTA CRUZ ITUNDUJIA": 1,
      "SANTA CRUZ PAPALUTLA": 0,
      "SANTA CRUZ XOXOCOTLÁN": 148,
      "SANTA CRUZ ZENZONTEPEC": 3,
      "SANTA INÉS DEL MONTE": 1,
      "SANTA LUCÍA DEL CAMINO": 84,
      "SANTA MARÍA ATZOMPA": 55,
      "SANTA MARÍA CHILCHOTLA": 4,
      "SANTA MARÍA COLOTEPEC": 3,
      "SANTA MARÍA COYOTEPEC": 1,
      "SANTA MARÍA DEL TULE": 13,
      "SANTA MARÍA ECATEPEC": 1,
      "SANTA MARÍA HUATULCO": 2,
      "SANTA MARÍA HUAZOLOTITLÁN": 1,
      "SANTA MARÍA JALAPA DEL MARQUÉS": 1,
      "SANTA MARÍA MIXTEQUILLA": 3,
      "SANTA MARÍA PETAPA": 0,
      "SANTA MARÍA PEÑOLES": 1,
      "SANTA MARÍA SOLA": 1,
      "SANTA MARÍA TEMAXCALTEPEC": 0,
      "SANTA MARÍA TLAHUITOLTEPEC": 1,
      "SANTA MARÍA TONAMECA": 2,
      "SANTA MARÍA ZACATEPEC": 0,
      "SANTIAGO AMOLTEPEC": 1,
      "SANTIAGO CHAZUMBA": 0,
      "SANTIAGO JUXTLAHUACA": 4,
      "SANTIAGO LAOLLAGA": 0,
      "SANTIAGO LAXOPA": 1,
      "SANTIAGO MATATLÁN": 0,
      "SANTIAGO PINOTEPA NACIONAL": 7,
      "SANTIAGO SUCHILQUITONGO": 0,
      "SANTIAGO TAMAZOLA": 1,
      "SANTIAGO TENANGO": 0,
      "SANTIAGO TLAZOYALTEPEC": 1,
      "SANTIAGO XIACUÍ": 0,
      "SANTIAGO YAVEO": 3,
      "SANTO DOMINGO NUXAÁ": 0,
      "SANTO DOMINGO TEHUANTEPEC": 5,
      "SANTO DOMINGO TEOJOMULCO": 1,
      "SANTO DOMINGO TOMALTEPEC": 4,
      "SANTO DOMINGO ZANATEPEC": 2,
      "SANTO TOMÁS MAZALTEPEC": 1,
      "SE DESCONOCE": 85,
      "SILACAYOÁPAM": 1,
      "SIN MUNICIPIO DE REFERENCIA": 26,
      "SOLEDAD ETLA": 0,
      "TANICHE": 0,
      "TEOTITLÁN DE FLORES MAGÓN": 1,
      "TEOTITLÁN DEL VALLE": 0,
      "TEZOATLÁN DE SEGURA Y LUNA": 1,
      "TLACOLULA DE MATAMOROS": 4,
      "TLALIXTAC DE CABRERA": 6,
      "TOTONTEPEC VILLA DE MORELOS": 1,
      "TRINIDAD ZAACHILA": 3,
      "UNIÓN HIDALGO": 1,
      "VALERIO TRUJANO": 2,
      "VILLA DE ETLA": 5,
      "VILLA DE TUTUTEPEC DE MELCHOR OCAMPO": 1,
      "VILLA DE ZAACHILA": 46,
      "VILLA SOLA DE VEGA": 3,
      "ZIMATLÁN DE ALVAREZ": 6
    },
    "Indeterminado": {
      "ABEJONES": 0,
      "ACATLÁN DE PÉREZ FIGUEROA": 0,
      "AGUA PRIETA": 0,
      "ANIMAS TRUJANO": 0,
      "ASUNCIÓN IXTALTEPEC": 0,
      "ASUNCIÓN NOCHIXTLÁN": 0,
      "ASUNCIÓN TLACOLULITA": 0,
      "AYOQUEZCO DE ALDAMA": 0,
      "CAPULÁLPAM DE MÉNDEZ": 0,
      "CHAHUITES": 0,
      "CHALCATONGO DE HIDALGO": 0,
      "CIUDAD IXTEPEC": 0,
      "COATECAS ALTAS": 0,
      "CONCEPCIÓN PÁPALO": 0,
      "CONSTANCIA DEL ROSARIO": 0,
      "COSOLAPA": 0,
      "COXCATLÁN": 0,
      "CUILÁPAM DE GUERRERO": 0,
      "EL ESPINAL": 0,
      "ELOXOCHITLÁN DE FLORES MAGÓN": 0,
      "GUADALUPE DE RAMÍREZ": 0,
      "GUELATAO DE JUÁREZ": 0,
      "GUEVEA DE HUMBOLDT": 0,
      "HEROICA CIUDAD DE EJUTLA DE CRESPO": 0,
      "HEROICA CIUDAD DE TLAXIACO": 0,
      "HUAJUAPAN DE LEÓN": 0,
      "HUAUTLA DE JIMÉNEZ": 0,
      "IXTLÁN DE JUÁREZ": 0,
      "JUCHITÁN DE ZARAGOZA": 0,
      "LA REFORMA": 0,
      "LOMA BONITA": 0,
      "MAGDALENA APASCO": 0,
      "MAGDALENA JALTEPEC": 0,
      "MAGDALENA MIXTEPEC": 0,
      "MAGDALENA OCOTLÁN": 0,
      "MATÍAS ROMERO AVENDAÑO": 0,
      "MAZATLÁN VILLA DE FLORES": 0,
      "MESONES HIDALGO": 0,
      "MIAHUATLÁN DE PORFIRIO DÍAZ": 0,
      "NAZARENO ETLA": 0,
      "OAXACA DE JUÁREZ": 0,
      "OCOTLÁN DE MORELOS": 0,
      "PINOTEPA DE DON LUIS": 0,
      "PLUMA HIDALGO": 0,
      "PUTLA VILLA DE GUERRERO": 0,
      "REYES ETLA": 0,
      "SALINA CRUZ": 0,
      "SAN AGUSTÍN ATENANGO": 0,
      "SAN AGUSTÍN DE LAS JUNTAS": 0,
      "SAN AGUSTÍN ETLA": 0,
      "SAN AGUSTÍN YATARENI": 0,
      "SAN ANDRÉS HUAYAPAM": 0,
      "SAN ANDRÉS IXTLAHUACA": 0,
      "SAN ANDRÉS ZAUTLA": 0,
      "SAN ANTONINO CASTILLO VELASCO": 0,
      "SAN ANTONINO EL ALTO": 0,
      "SAN ANTONIO DE LA CAL": 0,
      "SAN ANTONIO HUITEPEC": 0,
      "SAN BALTAZAR YATZACHI EL BAJO": 0,
      "SAN BARTOLO COYOTEPEC": 0,
      "SAN BERNARDO MIXTEPEC": 0,
      "SAN CRISTÓBAL AMATLÁN": 0,
      "SAN CRISTÓBAL LACHIRIOAG": 0,
      "SAN DIONISIO OCOTEPEC": 0,
      "SAN ESTEBAN ATATLAHUCA": 0,
      "SAN FELIPE JALAPA DE DÍAZ": 0,
      "SAN FELIPE USILA": 0,
      "SAN FRANCISCO IXHUATÁN": 0,
      "SAN FRANCISCO LACHIGOLÓ": 0,
      "SAN FRANCISCO TELIXTLAHUACA": 0,
      "SAN ILDEFONSO AMATLÁN": 0,
      "SAN ILDEFONSO VILLA ALTA": 0,
      "SAN JACINTO AMILPAS": 0,
      "SAN JERÓNIMO TAVICHE": 0,
      "SAN JOSÉ DEL PROGRESO": 0,
      "SAN JOSÉ LACHIGUIRI": 0,
      "SAN JOSÉ TENANGO": 0,
      "SAN JUAN BAUTISTA CUICATLÁN": 0,
      "SAN JUAN BAUTISTA GUELACHE": 0,
      "SAN JUAN BAUTISTA TUXTEPEC": 0,
      "SAN JUAN BAUTISTA VALLE NACIONAL": 0,
      "SAN JUAN COTZOCÓN": 0,
      "SAN JUAN GUELAVÍA": 0,
      "SAN JUAN GUICHICOVI": 0,
      "SAN JUAN JUQUILA MIXES": 0,
      "SAN JUAN JUQUILA VIJANOS": 0,
      "SAN JUAN LALANA": 0,
      "SAN JUAN MAZATLÁN": 0,
      "SAN JUAN MIXTEPEC JUXTLAHUACA": 0,
      "SAN JUAN QUIAHIJE": 0,
      "SAN JUAN TAMAZOLA": 0,
      "SAN JUAN TEITIPAC": 0,
      "SAN LORENZO CACAOTEPEC": 0,
      "SAN LORENZO TEXMELUCAN": 0,
      "SAN LUCAS OJITLÁN": 0,
      "SAN LUIS AMATLÁN": 0,
      "SAN MARTÍN TILCAJETE": 0,
      "SAN MATEO PEÑASCO": 0,
      "SAN MIGUEL CHICAHUA": 0,
      "SAN MIGUEL HUAUTLA": 0,
      "SAN MIGUEL MIXTEPEC": 0,
      "SAN MIGUEL QUETZALTEPEC": 0,
      "SAN MIGUEL SOYALTEPEC": 0,
      "SAN PABLO COATLÁN": 0,
      "SAN PABLO ETLA": 0,
      "SAN PABLO HUITZO": 0,
      "SAN PABLO HUIXTEPEC": 0,
      "SAN PABLO VILLA DE MITLA": 0,
      "SAN PEDRO CAJONOS": 0,
      "SAN PEDRO IXTLAHUACA": 0,
      "SAN PEDRO JOCOTIPAC": 0,
      "SAN PEDRO MIXTEPEC-JUQUILA": 0,
      "SAN PEDRO OCOTEPEC": 0,
      "SAN PEDRO POCHUTLA": 0,
      "SAN PEDRO TAPANATEPEC": 0,
      "SAN PEDRO TOTOLAPA": 0,
      "SAN PEDRO Y SAN PABLO AYUTLA": 0,
      "SAN PEDRO Y SAN PABLO TEPOSCOLULA": 0,
      "SAN PEDRO YANERI": 0,
      "SAN RAYMUNDO JALPAN": 0,
      "SAN SEBASTIÁN NICANANDUTA": 0,
      "SAN SEBASTIÁN TECOMAXTLAHUACA": 0,
      "SAN SEBASTIÁN TEITIPAC": 0,
      "SAN SEBASTIÁN TUTLA": 0,
      "SAN VICENTE COATLÁN": 0,
      "SANTA CATARINA JUQUILA": 0,
      "SANTA CATARINA MINAS": 0,
      "SANTA CATARINA QUIANÉ": 0,
      "SANTA CATARINA TAYATA": 0,
      "SANTA CRUZ AMILPAS": 0,
      "SANTA CRUZ ITUNDUJIA": 0,
      "SANTA CRUZ PAPALUTLA": 0,
      "SANTA CRUZ XOXOCOTLÁN": 0,
      "SANTA CRUZ ZENZONTEPEC": 0,
      "SANTA INÉS DEL MONTE": 0,
      "SANTA LUCÍA DEL CAMINO": 0,
      "SANTA MARÍA ATZOMPA": 0,
      "SANTA MARÍA CHILCHOTLA": 0,
      "SANTA MARÍA COLOTEPEC": 0,
      "SANTA MARÍA COYOTEPEC": 0,
      "SANTA MARÍA DEL TULE": 0,
      "SANTA MARÍA ECATEPEC": 0,
      "SANTA MARÍA HUATULCO": 0,
      "SANTA MARÍA HUAZOLOTITLÁN": 0,
      "SANTA MARÍA JALAPA DEL MARQUÉS": 0,
      "SANTA MARÍA MIXTEQUILLA": 0,
      "SANTA MARÍA PETAPA": 0,
      "SANTA MARÍA PEÑOLES": 0,
      "SANTA MARÍA SOLA": 0,
      "SANTA MARÍA TEMAXCALTEPEC": 0,
      "SANTA MARÍA TLAHUITOLTEPEC": 0,
      "SANTA MARÍA TONAMECA": 0,
      "SANTA MARÍA ZACATEPEC": 0,
      "SANTIAGO AMOLTEPEC": 0,
      "SANTIAGO CHAZUMBA": 0,
      "SANTIAGO JUXTLAHUACA": 0,
      "SANTIAGO LAOLLAGA": 0,
      "SANTIAGO LAXOPA": 0,
      "SANTIAGO MATATLÁN": 0,
      "SANTIAGO PINOTEPA NACIONAL": 0,
      "SANTIAGO SUCHILQUITONGO": 0,
      "SANTIAGO TAMAZOLA": 0,
      "SANTIAGO TENANGO": 0,
      "SANTIAGO TLAZOYALTEPEC": 0,
      "SANTIAGO XIACUÍ": 0,
      "SANTIAGO YAVEO": 0,
      "SANTO DOMINGO NUXAÁ": 0,
      "SANTO DOMINGO TEHUANTEPEC": 0,
      "SANTO DOMINGO TEOJOMULCO": 0,
      "SANTO DOMINGO TOMALTEPEC": 0,
      "SANTO DOMINGO ZANATEPEC": 0,
      "SANTO TOMÁS MAZALTEPEC": 0,
      "SE DESCONOCE": 5,
      "SILACAYOÁPAM": 0,
      "SIN MUNICIPIO DE REFERENCIA": 2,
      "SOLEDAD ETLA": 0,
      "TANICHE": 0,
      "TEOTITLÁN DE FLORES MAGÓN": 0,
      "TEOTITLÁN DEL VALLE": 0,
      "TEZOATLÁN DE SEGURA Y LUNA": 0,
      "TLACOLULA DE MATAMOROS": 0,
      "TLALIXTAC DE CABRERA": 0,
      "TOTONTEPEC VILLA DE MORELOS": 0,
      "TRINIDAD ZAACHILA": 0,
      "UNIÓN HIDALGO": 0,
      "VALERIO TRUJANO": 0,
      "VILLA DE ETLA": 0,
      "VILLA DE TUTUTEPEC DE MELCHOR OCAMPO": 0,
      "VILLA DE ZAACHILA": 0,
      "VILLA SOLA DE VEGA": 0,
      "ZIMATLÁN DE ALVAREZ": 0
    },
    "Mujeres": {
      "ABEJONES": 0,
      "ACATLÁN DE PÉREZ FIGUEROA": 0,
      "AGUA PRIETA": 1,
      "ANIMAS TRUJANO": 14,
      "ASUNCIÓN IXTALTEPEC": 0,
      "ASUNCIÓN NOCHIXTLÁN": 4,
      "ASUNCIÓN TLACOLULITA": 0,
      "AYOQUEZCO DE ALDAMA": 1,
      "CAPULÁLPAM DE MÉNDEZ": 0,
      "CHAHUITES": 0,
      "CHALCATONGO DE HIDALGO": 1,
      "CIUDAD IXTEPEC": 1,
      "COATECAS ALTAS": 0,
      "CONCEPCIÓN PÁPALO": 1,
      "CONSTANCIA DEL ROSARIO": 1,
      "COSOLAPA": 2,
      "COXCATLÁN": 0,
      "CUILÁPAM DE GUERRERO": 51,
      "EL ESPINAL": 1,
      "ELOXOCHITLÁN DE FLORES MAGÓN": 0,
      "GUADALUPE DE RAMÍREZ": 0,
      "GUELATAO DE JUÁREZ": 1,
      "GUEVEA DE HUMBOLDT": 0,
      "HEROICA CIUDAD DE EJUTLA DE CRESPO": 1,
      "HEROICA CIUDAD DE TLAXIACO": 3,
      "HUAJUAPAN DE LEÓN": 4,
      "HUAUTLA DE JIMÉNEZ": 0,
      "IXTLÁN DE JUÁREZ": 0,
      "JUCHITÁN DE ZARAGOZA": 5,
      "LA REFORMA": 1,
      "LOMA BONITA": 3,
      "MAGDALENA APASCO": 4,
      "MAGDALENA JALTEPEC": 0,
      "MAGDALENA MIXTEPEC": 2,
      "MAGDALENA OCOTLÁN": 0,
      "MATÍAS ROMERO AVENDAÑO": 0,
      "MAZATLÁN VILLA DE FLORES": 0,
      "MESONES HIDALGO": 0,
      "MIAHUATLÁN DE PORFIRIO DÍAZ": 8,
      "NAZARENO ETLA": 1,
      "OAXACA DE JUÁREZ": 1027,
      "OCOTLÁN DE MORELOS": 7,
      "PINOTEPA DE DON LUIS": 0,
      "PLUMA HIDALGO": 1,
      "PUTLA VILLA DE GUERRERO": 1,
      "REYES ETLA": 2,
      "SALINA CRUZ": 3,
      "SAN AGUSTÍN ATENANGO": 1,
      "SAN AGUSTÍN DE LAS JUNTAS": 31,
      "SAN AGUSTÍN ETLA": 2,
      "SAN AGUSTÍN YATARENI": 7,
      "SAN ANDRÉS HUAYAPAM": 9,
      "SAN ANDRÉS IXTLAHUACA": 4,
      "SAN ANDRÉS ZAUTLA": 3,
      "SAN ANTONINO CASTILLO VELASCO": 3,
      "SAN ANTONINO EL ALTO": 0,
      "SAN ANTONIO DE LA CAL": 89,
      "SAN ANTONIO HUITEPEC": 0,
      "SAN BALTAZAR YATZACHI EL BAJO": 0,
      "SAN BARTOLO COYOTEPEC": 40,
      "SAN BERNARDO MIXTEPEC": 0,
      "SAN CRISTÓBAL AMATLÁN": 0,
      "SAN CRISTÓBAL LACHIRIOAG": 0,
      "SAN DIONISIO OCOTEPEC": 0,
      "SAN ESTEBAN ATATLAHUCA": 0,
      "SAN FELIPE JALAPA DE DÍAZ": 0,
      "SAN FELIPE USILA": 2,
      "SAN FRANCISCO IXHUATÁN": 0,
      "SAN FRANCISCO LACHIGOLÓ": 1,
      "SAN FRANCISCO TELIXTLAHUACA": 2,
      "SAN ILDEFONSO AMATLÁN": 2,
      "SAN ILDEFONSO VILLA ALTA": 0,
      "SAN JACINTO AMILPAS": 45,
      "SAN JERÓNIMO TAVICHE": 0,
      "SAN JOSÉ DEL PROGRESO": 0,
      "SAN JOSÉ LACHIGUIRI": 1,
      "SAN JOSÉ TENANGO": 1,
      "SAN JUAN BAUTISTA CUICATLÁN": 1,
      "SAN JUAN BAUTISTA GUELACHE": 1,
      "SAN JUAN BAUTISTA TUXTEPEC": 10,
      "SAN JUAN BAUTISTA VALLE NACIONAL": 0,
      "SAN JUAN COTZOCÓN": 0,
      "SAN JUAN GUELAVÍA": 1,
      "SAN JUAN GUICHICOVI": 2,
      "SAN JUAN JUQUILA MIXES": 0,
      "SAN JUAN JUQUILA VIJANOS": 0,
      "SAN JUAN LALANA": 0,
      "SAN JUAN MAZATLÁN": 0,
      "SAN JUAN MIXTEPEC JUXTLAHUACA": 0,
      "SAN JUAN QUIAHIJE": 0,
      "SAN JUAN TAMAZOLA": 1,
      "SAN JUAN TEITIPAC": 0,
      "SAN LORENZO CACAOTEPEC": 6,
      "SAN LORENZO TEXMELUCAN": 0,
      "SAN LUCAS OJITLÁN": 0,
      "SAN LUIS AMATLÁN": 1,
      "SAN MARTÍN TILCAJETE": 0,
      "SAN MATEO PEÑASCO": 1,
      "SAN MIGUEL CHICAHUA": 0,
      "SAN MIGUEL HUAUTLA": 1,
      "SAN MIGUEL MIXTEPEC": 1,
      "SAN MIGUEL QUETZALTEPEC": 0,
      "SAN MIGUEL SOYALTEPEC": 0,
      "SAN PABLO COATLÁN": 0,
      "SAN PABLO ETLA": 13,
      "SAN PABLO HUITZO": 2,
      "SAN PABLO HUIXTEPEC": 2,
      "SAN PABLO VILLA DE MITLA": 4,
      "SAN PEDRO CAJONOS": 1,
      "SAN PEDRO IXTLAHUACA": 30,
      "SAN PEDRO JOCOTIPAC": 0,
      "SAN PEDRO MIXTEPEC-JUQUILA": 6,
      "SAN PEDRO OCOTEPEC": 2,
      "SAN PEDRO POCHUTLA": 3,
      "SAN PEDRO TAPANATEPEC": 0,
      "SAN PEDRO TOTOLAPA": 0,
      "SAN PEDRO Y SAN PABLO AYUTLA": 0,
      "SAN PEDRO Y SAN PABLO TEPOSCOLULA": 0,
      "SAN PEDRO YANERI": 0,
      "SAN RAYMUNDO JALPAN": 2,
      "SAN SEBASTIÁN NICANANDUTA": 0,
      "SAN SEBASTIÁN TECOMAXTLAHUACA": 0,
      "SAN SEBASTIÁN TEITIPAC": 1,
      "SAN SEBASTIÁN TUTLA": 41,
      "SAN VICENTE COATLÁN": 0,
      "SANTA CATARINA JUQUILA": 4,
      "SANTA CATARINA MINAS": 0,
      "SANTA CATARINA QUIANÉ": 2,
      "SANTA CATARINA TAYATA": 1,
      "SANTA CRUZ AMILPAS": 28,
      "SANTA CRUZ ITUNDUJIA": 0,
      "SANTA CRUZ PAPALUTLA": 1,
      "SANTA CRUZ XOXOCOTLÁN": 273,
      "SANTA CRUZ ZENZONTEPEC": 0,
      "SANTA INÉS DEL MONTE": 1,
      "SANTA LUCÍA DEL CAMINO": 142,
      "SANTA MARÍA ATZOMPA": 76,
      "SANTA MARÍA CHILCHOTLA": 0,
      "SANTA MARÍA COLOTEPEC": 2,
      "SANTA MARÍA COYOTEPEC": 7,
      "SANTA MARÍA DEL TULE": 18,
      "SANTA MARÍA ECATEPEC": 0,
      "SANTA MARÍA HUATULCO": 1,
      "SANTA MARÍA HUAZOLOTITLÁN": 0,
      "SANTA MARÍA JALAPA DEL MARQUÉS": 1,
      "SANTA MARÍA MIXTEQUILLA": 1,
      "SANTA MARÍA PETAPA": 1,
      "SANTA MARÍA PEÑOLES": 0,
      "SANTA MARÍA SOLA": 0,
      "SANTA MARÍA TEMAXCALTEPEC": 1,
      "SANTA MARÍA TLAHUITOLTEPEC": 0,
      "SANTA MARÍA TONAMECA": 0,
      "SANTA MARÍA ZACATEPEC": 2,
      "SANTIAGO AMOLTEPEC": 0,
      "SANTIAGO CHAZUMBA": 1,
      "SANTIAGO JUXTLAHUACA": 3,
      "SANTIAGO LAOLLAGA": 1,
      "SANTIAGO LAXOPA": 0,
      "SANTIAGO MATATLÁN": 1,
      "SANTIAGO PINOTEPA NACIONAL": 2,
      "SANTIAGO SUCHILQUITONGO": 3,
      "SANTIAGO TAMAZOLA": 1,
      "SANTIAGO TENANGO": 2,
      "SANTIAGO TLAZOYALTEPEC": 0,
      "SANTIAGO XIACUÍ": 1,
      "SANTIAGO YAVEO": 0,
      "SANTO DOMINGO NUXAÁ": 1,
      "SANTO DOMINGO TEHUANTEPEC": 5,
      "SANTO DOMINGO TEOJOMULCO": 0,
      "SANTO DOMINGO TOMALTEPEC": 4,
      "SANTO DOMINGO ZANATEPEC": 0,
      "SANTO TOMÁS MAZALTEPEC": 0,
      "SE DESCONOCE": 79,
      "SILACAYOÁPAM": 1,
      "SIN MUNICIPIO DE REFERENCIA": 21,
      "SOLEDAD ETLA": 1,
      "TANICHE": 1,
      "TEOTITLÁN DE FLORES MAGÓN": 1,
      "TEOTITLÁN DEL VALLE": 5,
      "TEZOATLÁN DE SEGURA Y LUNA": 0,
      "TLACOLULA DE MATAMOROS": 10,
      "TLALIXTAC DE CABRERA": 13,
      "TOTONTEPEC VILLA DE MORELOS": 0,
      "TRINIDAD ZAACHILA": 1,
      "UNIÓN HIDALGO": 1,
      "VALERIO TRUJANO": 0,
      "VILLA DE ETLA": 5,
      "VILLA DE TUTUTEPEC DE MELCHOR OCAMPO": 0,
      "VILLA DE ZAACHILA": 105,
      "VILLA SOLA DE VEGA": 1,
      "ZIMATLÁN DE ALVAREZ": 5
    }
  },
  "anual": {
    "Hombre": {
      "1.CIFRA SIN  AÑO DE REFERENCIA": 60,
      "1975": 2,
      "1977": 1,
      "1978": 3,
      "1979": 1,
      "1987": 1,
      "1994": 0,
      "1995": 1,
      "1997": 1,
      "1998": 0,
      "2000": 1,
      "2001": 3,
      "2002": 2,
      "2003": 0,
      "2004": 1,
      "2005": 7,
      "2006": 2,
      "2007": 23,
      "2008": 32,
      "2009": 15,
      "2010": 57,
      "2011": 131,
      "2012": 135,
      "2013": 135,
      "2014": 132,
      "2015": 109,
      "2016": 88,
      "2017": 106,
      "2018": 97,
      "2019": 186,
      "2020": 134,
      "2021": 137,
      "2022": 96,
      "2023": 77,
      "2024": 13
    },
    "Indeterminado": {
      "1.CIFRA SIN  AÑO DE REFERENCIA": 5,
      "1975": 0,
      "1977": 0,
      "1978": 0,
      "1979": 0,
      "1987": 0,
      "1994": 0,
      "1995": 0,
      "1997": 0,
      "1998": 0,
      "2000": 0,
      "2001": 0,
      "2002": 0,
      "2003": 0,
      "2004": 0,
      "2005": 0,
      "2006": 0,
      "2007": 0,
      "2008": 0,
      "2009": 0,
      "2010": 0,
      "2011": 0,
      "2012": 0,
      "2013": 0,
      "2014": 0,
      "2015": 0,
      "2016": 0,
      "2017": 0,
      "2018": 1,
      "2019": 1,
      "2020": 0,
      "2021": 0,
      "2022": 0,
      "2023": 0,
      "2024": 0
    },
    "Mujer": {
      "1.CIFRA SIN  AÑO DE REFERENCIA": 46,
      "1975": 1,
      "1977": 0,
      "1978": 0,
      "1979": 0,
      "1987": 0,
      "1994": 1,
      "1995": 0,
      "1997": 0,
      "1998": 1,
      "2000": 1,
      "2001": 2,
      "2002": 0,
      "2003": 1,
      "2004": 1,
      "2005": 2,
      "2006": 5,
      "2007": 14,
      "2008": 32,
      "2009": 16,
      "2010": 90,
      "2011": 212,
      "2012": 205,
      "2013": 218,
      "2014": 271,
      "2015": 191,
      "2016": 166,
      "2017": 168,
      "2018": 123,
      "2019": 191,
      "2020": 153,
      "2021": 145,
      "2022": 70,
      "2023": 33,
      "2024": 6
    }
  },
  "mensual_ultimo_anio": {
    "Hombre": {
      "2023-AGOSTO": 9,
      "2023-DICIEMBRE": 1,
      "2023-JULIO": 6,
      "2023-NOVIEMBRE": 5,
      "2023-OCTUBRE": 7,
      "2023-SEPTIEMBRE": 5,
      "2024-ABRIL": 1,
      "2024-ENERO": 2,
      "2024-FEBRERO": 4,
      "2024-JUNIO": 1,
      "2024-MARZO": 1,
      "2024-MAYO": 4
    },
    "Indeterminado": {
      "2023-AGOSTO": 0,
      "2023-DICIEMBRE": 0,
      "2023-JULIO": 0,
      "2023-NOVIEMBRE": 0,
      "2023-OCTUBRE": 0,
      "2023-SEPTIEMBRE": 0,
      "2024-ABRIL": 0,
      "2024-ENERO": 0,
      "2024-FEBRERO": 0,
      "2024-JUNIO": 0,
      "2024-MARZO": 0,
      "2024-MAYO": 0
    },
    "Mujer": {
      "2023-AGOSTO": 6,
      "2023-DICIEMBRE": 2,
      "2023-JULIO": 1,
      "2023-NOVIEMBRE": 4,
      "2023-OCTUBRE": 1,
      "2023-SEPTIEMBRE": 1,
      "2024-ABRIL": 2,
      "2024-ENERO": 1,
      "2024-FEBRERO": 0,
      "2024-JUNIO": 0,
      "2024-MARZO": 1,
      "2024-MAYO": 2
    }
  },
  "por_edad": {
    "Hombres": {
      "0": 3,
      "1": 13,
      "10": 14,
      "11": 13,
      "12": 26,
      "13": 47,
      "14": 68,
      "15": 64,
      "16": 85,
      "17": 79,
      "18": 45,
      "19": 25,
      "2": 18,
      "20": 40,
      "21": 41,
      "22": 45,
      "23": 27,
      "24": 40,
      "25": 39,
      "26": 47,
      "27": 31,
      "28": 46,
      "29": 30,
      "3": 10,
      "30": 40,
      "31": 29,
      "32": 33,
      "33": 29,
      "34": 32,
      "35": 31,
      "36": 38,
      "37": 31,
      "38": 22,
      "39": 25,
      "4": 12,
      "40": 23,
      "41": 24,
      "42": 20,
      "43": 25,
      "44": 17,
      "45": 17,
      "46": 17,
      "47": 18,
      "48": 10,
      "49": 13,
      "5": 9,
      "50": 16,
      "51": 15,
      "52": 13,
      "53": 9,
      "54": 12,
      "55": 5,
      "56": 8,
      "57": 13,
      "58": 13,
      "59": 9,
      "6": 6,
      "60": 10,
      "61": 7,
      "62": 9,
      "63": 5,
      "64": 5,
      "65": 10,
      "66": 3,
      "67": 7,
      "68": 13,
      "69": 7,
      "7": 13,
      "70": 6,
      "71": 9,
      "72": 7,
      "73": 7,
      "74": 7,
      "75": 6,
      "76": 6,
      "77": 6,
      "78": 5,
      "79": 7,
      "8": 4,
      "80": 7,
      "81": 2,
      "82": 6,
      "83": 4,
      "84": 1,
      "85": 4,
      "86": 5,
      "87": 3,
      "88": 4,
      "89": 1,
      "9": 13,
      "93": 2,
      "94": 1,
      "99": 1,
      "SIN EDAD DE REFERENCIA": 47
    },
    "Indeterminado": {
      "0": 0,
      "1": 0,
      "10": 0,
      "11": 0,
      "12": 0,
      "13": 0,
      "14": 0,
      "15": 0,
      "16": 0,
      "17": 0,
      "18": 0,
      "19": 0,
      "2": 0,
      "20": 0,
      "21": 0,
      "22": 0,
      "23": 0,
      "24": 0,
      "25": 0,
      "26": 1,
      "27": 0,
      "28": 0,
      "29": 0,
      "3": 0,
      "30": 0,
      "31": 0,
      "32": 0,
      "33": 0,
      "34": 0,
      "35": 0,
      "36": 0,
      "37": 0,
      "38": 0,
      "39": 0,
      "4": 0,
      "40": 0,
      "41": 0,
      "42": 0,
      "43": 1,
      "44": 0,
      "45": 0,
      "46": 0,
      "47": 0,
      "48": 0,
      "49": 0,
      "5": 0,
      "50": 0,
      "51": 0,
      "52": 0,
      "53": 0,
      "54": 0,
      "55": 0,
      "56": 0,
      "57": 0,
      "58": 0,
      "59": 0,
      "6": 0,
      "60": 0,
      "61": 0,
      "62": 0,
      "63": 0,
      "64": 0,
      "65": 0,
      "66": 0,
      "67": 0,
      "68": 0,
      "69": 0,
      "7": 0,
      "70": 0,
      "71": 0,
      "72": 0,
      "73": 0,
      "74": 0,
      "75": 0,
      "76": 0,
      "77": 0,
      "78": 0,
      "79": 0,
      "8": 0,
      "80": 0,
      "81": 0,
      "82": 0,
      "83": 0,
      "84": 0,
      "85": 0,
      "86": 0,
      "87": 0,
      "88": 0,
      "89": 0,
      "9": 0,
      "93": 0,
      "94": 0,
      "99": 0,
      "SIN EDAD DE REFERENCIA": 5
    },
    "Mujeres": {
      "0": 1,
      "1": 11,
      "10": 11,
      "11": 15,
      "12": 59,
      "13": 168,
      "14": 250,
      "15": 291,
      "16": 301,
      "17": 271,
      "18": 104,
      "19": 60,
      "2": 10,
      "20": 51,
      "21": 47,
      "22": 51,
      "23": 45,
      "24": 44,
      "25": 33,
      "26": 32,
      "27": 28,
      "28": 21,
      "29": 25,
      "3": 10,
      "30": 22,
      "31": 18,
      "32": 22,
      "33": 17,
      "34": 17,
      "35": 17,
      "36": 13,
      "37": 6,
      "38": 15,
      "39": 14,
      "4": 13,
      "40": 9,
      "41": 15,
      "42": 9,
      "43": 8,
      "44": 7,
      "45": 7,
      "46": 9,
      "47": 8,
      "48": 5,
      "49": 7,
      "5": 13,
      "50": 5,
      "51": 2,
      "52": 6,
      "53": 1,
      "54": 7,
      "55": 1,
      "56": 2,
      "57": 3,
      "58": 2,
      "59": 4,
      "6": 11,
      "60": 3,
      "61": 2,
      "62": 3,
      "63": 3,
      "64": 2,
      "65": 3,
      "66": 1,
      "67": 0,
      "68": 1,
      "69": 1,
      "7": 11,
      "70": 3,
      "71": 3,
      "72": 3,
      "73": 2,
      "74": 1,
      "75": 0,
      "76": 2,
      "77": 1,
      "78": 1,
      "79": 0,
      "8": 9,
      "80": 2,
      "81": 1,
      "82": 1,
      "83": 0,
      "84": 1,
      "85": 2,
      "86": 1,
      "87": 0,
      "88": 1,
      "89": 1,
      "9": 9,
      "93": 0,
      "94": 1,
      "99": 0,
      "SIN EDAD DE REFERENCIA": 36
    }
  },
  "por_nacionalidad": {
    "Hombres": {
      "ALEMANA": 0,
      "CHILENA": 0,
      "COLOMBIANA": 3,
      "CUBANA": 8,
      "DOMINICANA": 1,
      "ECUATORIANA": 0,
      "ESTADOUNIDENSE": 6,
      "GUATEMALTECA": 10,
      "HONDUREÑA": 5,
      "ISRAELI": 1,
      "MEXICANA": 1718,
      "NICARAGUENSE": 4,
      "SALVADORENA": 5,
      "SE DESCONOCE": 17,
      "VENEZOLANA": 11
    },
    "Indeterminado": {
      "ALEMANA": 0,
      "CHILENA": 0,
      "COLOMBIANA": 0,
      "CUBANA": 0,
      "DOMINICANA": 0,
      "ECUATORIANA": 0,
      "ESTADOUNIDENSE": 0,
      "GUATEMALTECA": 0,
      "HONDUREÑA": 0,
      "ISRAELI": 0,
      "MEXICANA": 2,
      "NICARAGUENSE": 0,
      "SALVADORENA": 0,
      "SE DESCONOCE": 5,
      "VENEZOLANA": 0
    },
    "Mujeres": {
      "ALEMANA": 1,
      "CHILENA": 1,
      "COLOMBIANA": 1,
      "CUBANA": 2,
      "DOMINICANA": 0,
      "ECUATORIANA": 1,
      "ESTADOUNIDENSE": 15,
      "GUATEMALTECA": 9,
      "HONDUREÑA": 3,
      "ISRAELI": 0,
      "MEXICANA": 2310,
      "NICARAGUENSE": 1,
      "SALVADORENA": 4,
      "SE DESCONOCE": 16,
      "VENEZOLANA": 1
    }
  },
  "parametros": {
    "titulo": "PERSONAS DESAPARECIDAS, NO LOCALIZADAS Y LOCALIZADAS",
    "id_estatus_victima": "0",
    "fecha_inicio": "",
    "fecha_fin": "",
    "id_estado": "20",
    "id_municipio": "0",
    "mostrar_fecha_nula": "0",
    "id_colonia": "0",
    "id_nacionalidad": "0",
    "edad_inicio": "",
    "edad_fin": "",
    "mostrar_edad_nula": "0",
    "id_hipotesis": "",
    "id_medio_conocimiento": "",
    "id_circunstancia": "",
    "tiene_discapacidad": "",
    "id_tipo_discapacidad": "0",
    "id_etnia": "0",
    "id_lengua": "0",
    "id_religion": "",
    "es_migrante": "",
    "id_estatus_migratorio": "0",
    "es_lgbttti": "",
    "es_servidor_publico": "",
    "es_defensor_dh": "",
    "es_periodista": "",
    "es_sindicalista": "",
    "es_ong": "",
    "id_hipotesis_no_localizacion": "0",
    "id_delito": "0"
  }
}