{
  "totales": {
    "PorcentajeDesaparecidos": "100.00",
    "PorcentajeLocalizados": "0.00",
    "PorcentajeLocalizadosCV": "0.00",
    "PorcentajeLocalizadosSV": "0.00",
    "PorcentajeSoloDesaparecidos": "0.00",
    "PorcentajeSoloNoLocalizados": "100.00",
    "TotalDesaparecidos": "626",
    "TotalGlobal": "626",
    "TotalLocalizados": "00",
    "TotalLocalizadosCV": "00",
    "TotalLocalizadosSV": "00",
    "TotalSoloDesaparecidos": "00",
    "TotalSoloNoLocalizados": "626"
  },
  "espacial": {
    "Hombres": {
      "AHOME": 189,
      "ANGOSTURA": 3,
      "BADIRAGUATO": 3,
      "CHOIX": 11,
      "CONCORDIA": 3,
      "CULIACÁN": 157,
      "EL FUERTE": 33,
      "ELOTA": 2,
      "ESCUINAPA": 6,
      "GUASAVE": 30,
      "MAZATLÁN": 93,
      "MOCORITO": 5,
      "NAVOLATO": 14,
      "ROSARIO": 13,
      "SALVADOR ALVARADO": 17,
      "SAN IGNACIO": 5,
      "SIN MUNICIPIO DE REFERENCIA": 2,
      "SINALOA": 8
    },
    "Indeterminado": {
      "AHOME": 0,
      "ANGOSTURA": 0,
      "BADIRAGUATO": 0,
      "CHOIX": 0,
      "CONCORDIA": 0,
      "CULIACÁN": 0,
      "EL FUERTE": 0,
      "ELOTA": 0,
      "ESCUINAPA": 0,
      "GUASAVE": 1,
      "MAZATLÁN": 0,
      "MOCORITO": 0,
      "NAVOLATO": 0,
      "ROSARIO": 0,
      "SALVADOR ALVARADO": 0,
      "SAN IGNACIO": 0,
      "SIN MUNICIPIO DE REFERENCIA": 0,
      "SINALOA": 0
    },
    "Mujeres": {
      "AHOME": 11,
      "ANGOSTURA": 0,
      "BADIRAGUATO": 0,
      "CHOIX": 0,
      "CONCORDIA": 0,
      "CULIACÁN": 4,
      "EL FUERTE": 0,
      "ELOTA": 0,
      "ESCUINAPA": 1,
      "GUASAVE": 6,
      "MAZATLÁN": 8,
      "MOCORITO": 0,
      "NAVOLATO": 0,
      "ROSARIO": 1,
      "SALVADOR ALVARADO": 0,
      "SAN IGNACIO": 0,
      "SIN MUNICIPIO DE REFERENCIA": 0,
      "SINALOA": 0
    }
  },
  "anual": {
    "Hombre": {
      "1.CIFRA SIN  AÑO DE REFERENCIA": 4,
      "1988": 1,
      "1992": 1,
      "1994": 1,
      "1998": 1,
      "2004": 2,
      "2005": 1,
      "2009": 1,
      "2010": 5,
      "2011": 7,
      "2012": 11,
      "2013": 19,
      "2014": 86,
      "2015": 124,
      "2016": 87,
      "2017": 2,
      "2018": 2,
      "2019": 5,
      "2020": 69,
      "2021": 78,
      "2022": 57,
      "2023": 25,
      "2024": 5
    },
    "Indeterminado": {
      "1.CIFRA SIN  AÑO DE REFERENCIA": 0,
      "1988": 0,
      "1992": 0,
      "1994": 0,
      "1998": 0,
      "2004": 0,
      "2005": 0,
      "2009": 0,
      "2010": 0,
      "2011": 0,
      "2012": 0,
      "2013": 0,
      "2014": 0,
      "2015": 0,
      "2016": 0,
      "2017": 0,
      "2018": 0,
      "2019": 0,
      "2020": 0,
      "2021": 1,
      "2022": 0,
      "2023": 0,
      "2024": 0
    },
    "Mujer": {
      "1.CIFRA SIN  AÑO DE REFERENCIA": 0,
      "1988": 0,
      "1992": 0,
      "1994": 0,
      "1998": 0,
      "2004": 0,
      "2005": 0,
      "2009": 0,
      "2010": 0,
      "2011": 0,
      "2012": 1,
      "2013": 4,
      "2014": 4,
      "2015": 6,
      "2016": 8,
      "2017": 0,
      "2018": 0,
      "2019": 0,
      "2020": 3,
      "2021": 0,
      "2022": 5,
      "2023": 0,
      "2024": 0
    }
  },
  "mensual_ultimo_anio": {
    "Hombre": {
      "2022-DICIEMBRE": 1,
      "2023-ABRIL": 2,
      "2023-ENERO": 2,
      "2023-FEBRERO": 3,
      "2023-JUNIO": 6,
      "2023-MARZO": 5,
      "2023-MAYO": 6,
      "2023-SEPTIEMBRE": 1,
      "2024-ABRIL": 1,
      "2024-ENERO": 1,
      "2024-FEBRERO": 1,
      "2024-MARZO": 2
    },
    "Indeterminado": {
      "2022-DICIEMBRE": 0,
      "2023-ABRIL": 0,
      "2023-ENERO": 0,
      "2023-FEBRERO": 0,
      "2023-JUNIO": 0,
      "2023-MARZO": 0,
      "2023-MAYO": 0,
      "2023-SEPTIEMBRE": 0,
      "2024-ABRIL": 0,
      "2024-ENERO": 0,
      "2024-FEBRERO": 0,
      "2024-MARZO": 0
    },
    "Mujer": {
      "2022-DICIEMBRE": 0,
      "2023-ABRIL": 0,
      "2023-ENERO": 0,
      "2023-FEBRERO": 0,
      "2023-JUNIO": 0,
      "2023-MARZO": 0,
      "2023-MAYO": 0,
      "2023-SEPTIEMBRE": 0,
      "2024-ABRIL": 0,
      "2024-ENERO": 0,
      "2024-FEBRERO": 0,
      "2024-MARZO": 0
    }
  },
  "por_edad": {
    "Hombres": {
      "1": 1,
      "14": 1,
      "16": 3,
      "17": 1,
      "18": 12,
      "19": 23,
      "20": 14,
      "21": 12,
      "22": 17,
      "23": 12,
      "24": 22,
      "25": 30,
      "26": 18,
      "27": 20,
      "28": 23,
      "29": 16,
      "30": 17,
      "31": 22,
      "32": 23,
      "33": 17,
      "34": 15,
      "35": 9,
      "36": 13,
      "37": 20,
      "38": 17,
      "39": 16,
      "40": 15,
      "41": 17,
      "42": 17,
      "43": 19,
      "44": 13,
      "45": 8,
      "46": 10,
      "47": 9,
      "48": 9,
      "49": 6,
      "50": 4,
      "51": 2,
      "52": 6,
      "53": 6,
      "54": 9,
      "55": 2,
      "56": 6,
      "57": 4,
      "58": 2,
      "59": 5,
      "60": 2,
      "61": 2,
      "62": 4,
      "63": 1,
      "65": 1,
      "66": 1,
      "67": 1,
      "68": 2,
      "70": 1,
      "71": 2,
      "72": 1,
      "73": 0,
      "74": 1,
      "76": 1,
      "SIN EDAD DE REFERENCIA": 11
    },
    "Indeterminado": {
      "1": 0,
      "14": 0,
      "16": 0,
      "17": 0,
      "18": 0,
      "19": 0,
      "20": 0,
      "21": 0,
      "22": 0,
      "23": 0,
      "24": 0,
      "25": 0,
      "26": 0,
      "27": 0,
      "28": 0,
      "29": 1,
      "30": 0,
      "31": 0,
      "32": 0,
      "33": 0,
      "34": 0,
      "35": 0,
      "36": 0,
      "37": 0,
      "38": 0,
      "39": 0,
      "40": 0,
      "41": 0,
      "42": 0,
      "43": 0,
      "44": 0,
      "45": 0,
      "46": 0,
      "47": 0,
      "48": 0,
      "49": 0,
      "50": 0,
      "51": 0,
      "52": 0,
      "53": 0,
      "54": 0,
      "55": 0,
      "56": 0,
      "57": 0,
      "58": 0,
      "59": 0,
      "60": 0,
      "61": 0,
      "62": 0,
      "63": 0,
      "65": 0,
      "66": 0,
      "67": 0,
      "68": 0,
      "70": 0,
      "71": 0,
      "72": 0,
      "73": 0,
      "74": 0,
      "76": 0,
      "SIN EDAD DE REFERENCIA": 0
    },
    "Mujeres": {
      "1": 0,
      "14": 0,
      "16": 0,
      "17": 0,
      "18": 1,
      "19": 0,
      "20": 2,
      "21": 2,
      "22": 1,
      "23": 2,
      "24": 2,
      "25": 0,
      "26": 0,
      "27": 2,
      "28": 4,
      "29": 0,
      "30": 1,
      "31": 1,
      "32": 0,
      "33": 2,
      "34": 3,
      "35": 1,
      "36": 0,
      "37": 1,
      "38": 0,
      "39": 0,
      "40": 0,
      "41": 0,
      "42": 1,
      "43": 0,
      "44": 0,
      "45": 0,
      "46": 0,
      "47": 1,
      "48": 0,
      "49": 0,
      "50": 0,
      "51": 2,
      "52": 0,
      "53": 0,
      "54": 1,
      "55": 0,
      "56": 0,
      "57": 0,
      "58": 0,
      "59": 0,
      "60": 0,
      "61": 0,
      "62": 0,
      "63": 0,
      "65": 0,
      "66": 0,
      "67": 0,
      "68": 0,
      "70": 0,
      "71": 0,
      "72": 0,
      "73": 1,
      "74": 0,
      "76": 0,
      "SIN EDAD DE REFERENCIA": 0
    }
  },
  "por_nacionalidad": {
    "Hombres": {
      "MEXICANA": 594
    },
    "Indeterminado": {
      "MEXICANA": 1
    },
    "Mujeres": {
      "MEXICANA": 31
    }
  },
  "parametros": {
    "titulo": "PERSONAS NO LOCALIZADAS",
    "id_estatus_victima": "5",
    "fecha_inicio": "",
    "fecha_fin": "",
    "id_estado": "25",
    "id_municipio": "0",
    "mostrar_fecha_nula": "0",
    "id_colonia": "0",
    "id_nacionalidad": "0",
    "edad_inicio": "",
    "edad_fin": "",
    "mostrar_edad_nula": "0",
    "id_hipotesis": "",
    "id_medio_conocimiento": "",
    "id_circunstancia": "",
    "tiene_discapacidad": "",
    "id_tipo_discapacidad": "0",
    "id_etnia": "0",
    "id_lengua": "0",
    "id_religion": "",
    "es_migrante": "",
    "id_estatus_migratorio": "0",
    "es_lgbttti": "",
    "es_servidor_publico": "",
    "es_defensor_dh": "",
    "es_periodista": "",
    "es_sindicalista": "",
    "es_ong": "",
    "id_hipotesis_no_localizacion": "0",
    "id_delito": "0"
  }
}