{
  "totales": {
    "PorcentajeDesaparecidos": "0.00",
    "PorcentajeLocalizados": "100.00",
    "PorcentajeLocalizadosCV": "0.00",
    "PorcentajeLocalizadosSV": "100.00",
    "PorcentajeSoloDesaparecidos": "0.00",
    "PorcentajeSoloNoLocalizados": "0.00",
    "TotalDesaparecidos": "00",
    "TotalGlobal": "741",
    "TotalLocalizados": "741",
    "TotalLocalizadosCV": "00",
    "TotalLocalizadosSV": "741",
    "TotalSoloDesaparecidos": "00",
    "TotalSoloNoLocalizados": "00"
  },
  "espacial": {
    "Hombres": {
      "ACAJETE": 1,
      "ACAYUCAN": 3,
      "ACTOPAN": 3,
      "AGUA DULCE": 1,
      "ALPATLÁHUAC": 1,
      "ALTO LUCERO DE GUTIÉRREZ BARRIOS": 1,
      "ALTOTONGA": 2,
      "ALVARADO": 3,
      "AMATLÁN DE LOS REYES": 7,
      "ANGEL R. CABADA": 1,
      "ATOYAC": 2,
      "ATZACAN": 1,
      "ATZALAN": 2,
      "BANDERILLA": 1,
      "BENITO JUÁREZ": 2,
      "BOCA DEL RÍO": 6,
      "CAMERINO Z. MENDOZA": 4,
      "CARLOS A. CARRILLO": 6,
      "CARRILLO PUERTO": 1,
      "CATEMACO": 2,
      "CAZONES": 1,
      "CHACALTIANGUIS": 1,
      "CHICONQUIACO": 1,
      "CHICONTEPEC": 0,
      "CHINAMECA": 1,
      "CHOCAMÁN": 2,
      "CHONTLA": 1,
      "COATEPEC": 13,
      "COATZACOALCOS": 25,
      "COATZINTLA": 4,
      "COSAMALOAPAN DE CARPIO": 6,
      "COSCOMATEPEC": 1,
      "COSOLEACAQUE": 3,
      "COYUTLA": 1,
      "CUICHAPA": 1,
      "CUITLÁHUAC": 1,
      "CÓRDOBA": 26,
      "EL HIGO": 1,
      "EMILIANO ZAPATA": 10,
      "FILOMENO MATA": 1,
      "FORTÍN": 7,
      "GUTIÉRREZ ZAMORA": 3,
      "HUATUSCO": 2,
      "HUAYACOCOTLA": 0,
      "HUEYAPAN DE OCAMPO": 1,
      "HUILOAPAN": 1,
      "ISLA": 6,
      "IXHUACÁN DE LOS REYES": 0,
      "IXHUATLANCILLO": 1,
      "IXHUATLÁN DE MADERO": 0,
      "IXHUATLÁN DEL CAFÉ": 2,
      "IXTACZOQUITLÁN": 13,
      "JALACINGO": 1,
      "JAMAPA": 2,
      "JILOTEPEC": 1,
      "JOSÉ AZUETA": 1,
      "JUAN RODRÍGUEZ CLARA": 2,
      "JÁLTIPAN": 2,
      "LA ANTIGUA": 4,
      "LA PERLA": 2,
      "LAS CHOAPAS": 2,
      "LAS MINAS": 1,
      "LAS VIGAS DE RAMÍREZ": 2,
      "LERDO DE TEJADA": 2,
      "MAGDALENA": 1,
      "MALTRATA": 3,
      "MARIANO ESCOBEDO": 3,
      "MARTÍNEZ DE LA TORRE": 13,
      "MEDELLÍN": 3,
      "MINATITLÁN": 7,
      "MISANTLA": 6,
      "MOLOACÁN": 2,
      "NANCHITAL DE LÁZARO CÁRDENAS DEL RÍO": 2,
      "NAOLINCO": 5,
      "NARANJAL": 1,
      "NARANJOS AMATLÁN": 1,
      "NOGALES": 6,
      "OLUTA": 0,
      "OMEALCA": 2,
      "ORIZABA": 19,
      "OZULUAMA DE MASCAREÑAS": 2,
      "PAPANTLA": 15,
      "PASO DE OVEJAS": 1,
      "PASO DEL MACHO": 3,
      "PEROTE": 5,
      "PLAYA VICENTE": 4,
      "POZA RICA DE HIDALGO": 21,
      "PUEBLO VIEJO": 2,
      "PUENTE NACIONAL": 1,
      "PÁNUCO": 4,
      "RAFAEL DELGADO": 3,
      "RAFAEL LUCIO": 1,
      "RÍO BLANCO": 7,
      "SALTABARRANCA": 1,
      "SAN ANDRÉS TUXTLA": 2,
      "SAN JUAN EVANGELISTA": 1,
      "SAN RAFAEL": 1,
      "SANTIAGO SOCHIAPAN": 1,
      "SAYULA DE ALEMÁN": 2,
      "SE DESCONOCE": 53,
      "SIN MUNICIPIO DE REFERENCIA": 5,
      "SOCONUSCO": 1,
      "TAMALÍN": 1,
      "TAMIAHUA": 1,
      "TANTOYUCA": 1,
      "TEMAPACHE": 11,
      "TEOCELO": 1,
      "TEPETLÁN": 1,
      "TEPETZINTLA": 1,
      "TEZONAPA": 7,
      "TIERRA BLANCA": 8,
      "TIHUATLÁN": 4,
      "TLACOTALPAN": 1,
      "TLACOTEPEC DE MEJÍA": 1,
      "TLAPACOYAN": 4,
      "TOTUTLA": 1,
      "TRES VALLES": 2,
      "TÚXPAM": 18,
      "URSULO GALVÁN": 3,
      "VEGA DE ALATORRE": 4,
      "VERACRUZ": 41,
      "XALAPA": 92,
      "XICO": 3,
      "YANGA": 9,
      "ZACUALPAN": 1,
      "ZONGOLICA": 2
    },
    "Indeterminado": {
      "ACAJETE": 0,
      "ACAYUCAN": 0,
      "ACTOPAN": 0,
      "AGUA DULCE": 0,
      "ALPATLÁHUAC": 0,
      "ALTO LUCERO DE GUTIÉRREZ BARRIOS": 0,
      "ALTOTONGA": 0,
      "ALVARADO": 0,
      "AMATLÁN DE LOS REYES": 0,
      "ANGEL R. CABADA": 0,
      "ATOYAC": 0,
      "ATZACAN": 0,
      "ATZALAN": 0,
      "BANDERILLA": 0,
      "BENITO JUÁREZ": 0,
      "BOCA DEL RÍO": 0,
      "CAMERINO Z. MENDOZA": 0,
      "CARLOS A. CARRILLO": 0,
      "CARRILLO PUERTO": 0,
      "CATEMACO": 0,
      "CAZONES": 0,
      "CHACALTIANGUIS": 0,
      "CHICONQUIACO": 0,
      "CHICONTEPEC": 0,
      "CHINAMECA": 0,
      "CHOCAMÁN": 0,
      "CHONTLA": 0,
      "COATEPEC": 0,
      "COATZACOALCOS": 0,
      "COATZINTLA": 0,
      "COSAMALOAPAN DE CARPIO": 0,
      "COSCOMATEPEC": 0,
      "COSOLEACAQUE": 0,
      "COYUTLA": 0,
      "CUICHAPA": 0,
      "CUITLÁHUAC": 0,
      "CÓRDOBA": 0,
      "EL HIGO": 0,
      "EMILIANO ZAPATA": 0,
      "FILOMENO MATA": 0,
      "FORTÍN": 0,
      "GUTIÉRREZ ZAMORA": 0,
      "HUATUSCO": 0,
      "HUAYACOCOTLA": 0,
      "HUEYAPAN DE OCAMPO": 0,
      "HUILOAPAN": 0,
      "ISLA": 0,
      "IXHUACÁN DE LOS REYES": 0,
      "IXHUATLANCILLO": 0,
      "IXHUATLÁN DE MADERO": 0,
      "IXHUATLÁN DEL CAFÉ": 0,
      "IXTACZOQUITLÁN": 0,
      "JALACINGO": 0,
      "JAMAPA": 0,
      "JILOTEPEC": 0,
      "JOSÉ AZUETA": 0,
      "JUAN RODRÍGUEZ CLARA": 0,
      "JÁLTIPAN": 0,
      "LA ANTIGUA": 0,
      "LA PERLA": 0,
      "LAS CHOAPAS": 0,
      "LAS MINAS": 0,
      "LAS VIGAS DE RAMÍREZ": 0,
      "LERDO DE TEJADA": 0,
      "MAGDALENA": 0,
      "MALTRATA": 0,
      "MARIANO ESCOBEDO": 0,
      "MARTÍNEZ DE LA TORRE": 0,
      "MEDELLÍN": 0,
      "MINATITLÁN": 0,
      "MISANTLA": 0,
      "MOLOACÁN": 0,
      "NANCHITAL DE LÁZARO CÁRDENAS DEL RÍO": 0,
      "NAOLINCO": 0,
      "NARANJAL": 0,
      "NARANJOS AMATLÁN": 0,
      "NOGALES": 0,
      "OLUTA": 0,
      "OMEALCA": 0,
      "ORIZABA": 0,
      "OZULUAMA DE MASCAREÑAS": 0,
      "PAPANTLA": 0,
      "PASO DE OVEJAS": 0,
      "PASO DEL MACHO": 0,
      "PEROTE": 0,
      "PLAYA VICENTE": 0,
      "POZA RICA DE HIDALGO": 0,
      "PUEBLO VIEJO": 0,
      "PUENTE NACIONAL": 0,
      "PÁNUCO": 0,
      "RAFAEL DELGADO": 0,
      "RAFAEL LUCIO": 0,
      "RÍO BLANCO": 0,
      "SALTABARRANCA": 0,
      "SAN ANDRÉS TUXTLA": 0,
      "SAN JUAN EVANGELISTA": 0,
      "SAN RAFAEL": 0,
      "SANTIAGO SOCHIAPAN": 0,
      "SAYULA DE ALEMÁN": 0,
      "SE DESCONOCE": 0,
      "SIN MUNICIPIO DE REFERENCIA": 0,
      "SOCONUSCO": 0,
      "TAMALÍN": 0,
      "TAMIAHUA": 0,
      "TANTOYUCA": 0,
      "TEMAPACHE": 0,
      "TEOCELO": 0,
      "TEPETLÁN": 0,
      "TEPETZINTLA": 0,
      "TEZONAPA": 0,
      "TIERRA BLANCA": 0,
      "TIHUATLÁN": 0,
      "TLACOTALPAN": 0,
      "TLACOTEPEC DE MEJÍA": 0,
      "TLAPACOYAN": 0,
      "TOTUTLA": 0,
      "TRES VALLES": 0,
      "TÚXPAM": 0,
      "URSULO GALVÁN": 0,
      "VEGA DE ALATORRE": 0,
      "VERACRUZ": 0,
      "XALAPA": 0,
      "XICO": 0,
      "YANGA": 0,
      "ZACUALPAN": 0,
      "ZONGOLICA": 0
    },
    "Mujeres": {
      "ACAJETE": 2,
      "ACAYUCAN": 0,
      "ACTOPAN": 0,
      "AGUA DULCE": 0,
      "ALPATLÁHUAC": 0,
      "ALTO LUCERO DE GUTIÉRREZ BARRIOS": 0,
      "ALTOTONGA": 1,
      "ALVARADO": 0,
      "AMATLÁN DE LOS REYES": 0,
      "ANGEL R. CABADA": 0,
      "ATOYAC": 0,
      "ATZACAN": 0,
      "ATZALAN": 0,
      "BANDERILLA": 0,
      "BENITO JUÁREZ": 0,
      "BOCA DEL RÍO": 0,
      "CAMERINO Z. MENDOZA": 1,
      "CARLOS A. CARRILLO": 0,
      "CARRILLO PUERTO": 0,
      "CATEMACO": 0,
      "CAZONES": 0,
      "CHACALTIANGUIS": 0,
      "CHICONQUIACO": 0,
      "CHICONTEPEC": 1,
      "CHINAMECA": 0,
      "CHOCAMÁN": 0,
      "CHONTLA": 0,
      "COATEPEC": 1,
      "COATZACOALCOS": 1,
      "COATZINTLA": 2,
      "COSAMALOAPAN DE CARPIO": 0,
      "COSCOMATEPEC": 0,
      "COSOLEACAQUE": 1,
      "COYUTLA": 0,
      "CUICHAPA": 0,
      "CUITLÁHUAC": 0,
      "CÓRDOBA": 6,
      "EL HIGO": 0,
      "EMILIANO ZAPATA": 0,
      "FILOMENO MATA": 0,
      "FORTÍN": 1,
      "GUTIÉRREZ ZAMORA": 1,
      "HUATUSCO": 0,
      "HUAYACOCOTLA": 1,
      "HUEYAPAN DE OCAMPO": 0,
      "HUILOAPAN": 0,
      "ISLA": 1,
      "IXHUACÁN DE LOS REYES": 1,
      "IXHUATLANCILLO": 1,
      "IXHUATLÁN DE MADERO": 1,
      "IXHUATLÁN DEL CAFÉ": 2,
      "IXTACZOQUITLÁN": 0,
      "JALACINGO": 0,
      "JAMAPA": 0,
      "JILOTEPEC": 0,
      "JOSÉ AZUETA": 0,
      "JUAN RODRÍGUEZ CLARA": 0,
      "JÁLTIPAN": 0,
      "LA ANTIGUA": 2,
      "LA PERLA": 0,
      "LAS CHOAPAS": 0,
      "LAS MINAS": 0,
      "LAS VIGAS DE RAMÍREZ": 0,
      "LERDO DE TEJADA": 0,
      "MAGDALENA": 0,
      "MALTRATA": 0,
      "MARIANO ESCOBEDO": 0,
      "MARTÍNEZ DE LA TORRE": 0,
      "MEDELLÍN": 1,
      "MINATITLÁN": 1,
      "MISANTLA": 0,
      "MOLOACÁN": 0,
      "NANCHITAL DE LÁZARO CÁRDENAS DEL RÍO": 0,
      "NAOLINCO": 2,
      "NARANJAL": 0,
      "NARANJOS AMATLÁN": 0,
      "NOGALES": 2,
      "OLUTA": 1,
      "OMEALCA": 1,
      "ORIZABA": 0,
      "OZULUAMA DE MASCAREÑAS": 0,
      "PAPANTLA": 4,
      "PASO DE OVEJAS": 0,
      "PASO DEL MACHO": 1,
      "PEROTE": 3,
      "PLAYA VICENTE": 0,
      "POZA RICA DE HIDALGO": 5,
      "PUEBLO VIEJO": 0,
      "PUENTE NACIONAL": 0,
      "PÁNUCO": 0,
      "RAFAEL DELGADO": 0,
      "RAFAEL LUCIO": 1,
      "RÍO BLANCO": 4,
      "SALTABARRANCA": 0,
      "SAN ANDRÉS TUXTLA": 1,
      "SAN JUAN EVANGELISTA": 0,
      "SAN RAFAEL": 0,
      "SANTIAGO SOCHIAPAN": 0,
      "SAYULA DE ALEMÁN": 0,
      "SE DESCONOCE": 9,
      "SIN MUNICIPIO DE REFERENCIA": 0,
      "SOCONUSCO": 0,
      "TAMALÍN": 0,
      "TAMIAHUA": 0,
      "TANTOYUCA": 1,
      "TEMAPACHE": 1,
      "TEOCELO": 0,
      "TEPETLÁN": 0,
      "TEPETZINTLA": 0,
      "TEZONAPA": 1,
      "TIERRA BLANCA": 2,
      "TIHUATLÁN": 2,
      "TLACOTALPAN": 1,
      "TLACOTEPEC DE MEJÍA": 0,
      "TLAPACOYAN": 1,
      "TOTUTLA": 0,
      "TRES VALLES": 0,
      "TÚXPAM": 1,
      "URSULO GALVÁN": 0,
      "VEGA DE ALATORRE": 0,
      "VERACRUZ": 15,
      "XALAPA": 16,
      "XICO": 0,
      "YANGA": 0,
      "ZACUALPAN": 0,
      "ZONGOLICA": 1
    }
  },
  "anual": {
    "Hombre": {
      "1.CIFRA SIN  AÑO DE REFERENCIA": 53,
      "2008": 1,
      "2009": 1,
      "2010": 4,
      "2011": 8,
      "2012": 15,
      "2013": 27,
      "2014": 37,
      "2015": 14,
      "2016": 38,
      "2017": 23,
      "2018": 14,
      "2019": 45,
      "2020": 81,
      "2021": 88,
      "2022": 102,
      "2023": 83,
      "2024": 2
    },
    "Indeterminado": {
      "1.CIFRA SIN  AÑO DE REFERENCIA": 0,
      "2008": 0,
      "2009": 0,
      "2010": 0,
      "2011": 0,
      "2012": 0,
      "2013": 0,
      "2014": 0,
      "2015": 0,
      "2016": 0,
      "2017": 0,
      "2018": 0,
      "2019": 0,
      "2020": 0,
      "2021": 0,
      "2022": 0,
      "2023": 0,
      "2024": 0
    },
    "Mujer": {
      "1.CIFRA SIN  AÑO DE REFERENCIA": 6,
      "2008": 0,
      "2009": 0,
      "2010": 0,
      "2011": 3,
      "2012": 2,
      "2013": 0,
      "2014": 4,
      "2015": 0,
      "2016": 14,
      "2017": 3,
      "2018": 5,
      "2019": 10,
      "2020": 11,
      "2021": 19,
      "2022": 10,
      "2023": 15,
      "2024": 3
    }
  },
  "mensual_ultimo_anio": {
    "Hombre": {
      "2023-ABRIL": 11,
      "2023-AGOSTO": 10,
      "2023-DICIEMBRE": 3,
      "2023-JULIO": 8,
      "2023-JUNIO": 9,
      "2023-MARZO": 6,
      "2023-MAYO": 4,
      "2023-NOVIEMBRE": 4,
      "2023-OCTUBRE": 2,
      "2023-SEPTIEMBRE": 9,
      "2024-ENERO": 0,
      "2024-FEBRERO": 2
    },
    "Indeterminado": {
      "2023-ABRIL": 0,
      "2023-AGOSTO": 0,
      "2023-DICIEMBRE": 0,
      "2023-JULIO": 0,
      "2023-JUNIO": 0,
      "2023-MARZO": 0,
      "2023-MAYO": 0,
      "2023-NOVIEMBRE": 0,
      "2023-OCTUBRE": 0,
      "2023-SEPTIEMBRE": 0,
      "2024-ENERO": 0,
      "2024-FEBRERO": 0
    },
    "Mujer": {
      "2023-ABRIL": 2,
      "2023-AGOSTO": 1,
      "2023-DICIEMBRE": 0,
      "2023-JULIO": 0,
      "2023-JUNIO": 2,
      "2023-MARZO": 1,
      "2023-MAYO": 5,
      "2023-NOVIEMBRE": 1,
      "2023-OCTUBRE": 0,
      "2023-SEPTIEMBRE": 0,
      "2024-ENERO": 2,
      "2024-FEBRERO": 1
    }
  },
  "por_edad": {
    "Hombres": {
      "0": 1,
      "1": 1,
      "12": 0,
      "124": 1,
      "13": 1,
      "14": 0,
      "15": 1,
      "16": 8,
      "17": 10,
      "18": 12,
      "19": 7,
      "2": 1,
      "20": 22,
      "21": 10,
      "22": 13,
      "23": 20,
      "24": 23,
      "25": 19,
      "26": 23,
      "27": 14,
      "28": 28,
      "29": 22,
      "3": 1,
      "30": 20,
      "31": 12,
      "32": 15,
      "33": 12,
      "34": 15,
      "35": 20,
      "36": 13,
      "37": 8,
      "38": 18,
      "39": 13,
      "40": 10,
      "41": 10,
      "42": 18,
      "43": 9,
      "44": 6,
      "45": 13,
      "46": 12,
      "47": 5,
      "48": 5,
      "49": 9,
      "50": 6,
      "51": 7,
      "52": 2,
      "53": 10,
      "54": 3,
      "55": 6,
      "56": 7,
      "57": 3,
      "58": 6,
      "59": 7,
      "60": 8,
      "61": 3,
      "62": 5,
      "63": 3,
      "64": 1,
      "65": 3,
      "66": 1,
      "67": 2,
      "68": 3,
      "70": 2,
      "71": 4,
      "72": 1,
      "73": 4,
      "74": 2,
      "75": 3,
      "76": 1,
      "77": 1,
      "78": 2,
      "79": 2,
      "80": 1,
      "81": 1,
      "82": 0,
      "83": 3,
      "84": 1,
      "85": 2,
      "86": 3,
      "87": 1,
      "89": 1,
      "93": 1,
      "SIN EDAD DE REFERENCIA": 34
    },
    "Indeterminado": {
      "0": 0,
      "1": 0,
      "12": 0,
      "124": 0,
      "13": 0,
      "14": 0,
      "15": 0,
      "16": 0,
      "17": 0,
      "18": 0,
      "19": 0,
      "2": 0,
      "20": 0,
      "21": 0,
      "22": 0,
      "23": 0,
      "24": 0,
      "25": 0,
      "26": 0,
      "27": 0,
      "28": 0,
      "29": 0,
      "3": 0,
      "30": 0,
      "31": 0,
      "32": 0,
      "33": 0,
      "34": 0,
      "35": 0,
      "36": 0,
      "37": 0,
      "38": 0,
      "39": 0,
      "40": 0,
      "41": 0,
      "42": 0,
      "43": 0,
      "44": 0,
      "45": 0,
      "46": 0,
      "47": 0,
      "48": 0,
      "49": 0,
      "50": 0,
      "51": 0,
      "52": 0,
      "53": 0,
      "54": 0,
      "55": 0,
      "56": 0,
      "57": 0,
      "58": 0,
      "59": 0,
      "60": 0,
      "61": 0,
      "62": 0,
      "63": 0,
      "64": 0,
      "65": 0,
      "66": 0,
      "67": 0,
      "68": 0,
      "70": 0,
      "71": 0,
      "72": 0,
      "73": 0,
      "74": 0,
      "75": 0,
      "76": 0,
      "77": 0,
      "78": 0,
      "79": 0,
      "80": 0,
      "81": 0,
      "82": 0,
      "83": 0,
      "84": 0,
      "85": 0,
      "86": 0,
      "87": 0,
      "89": 0,
      "93": 0,
      "SIN EDAD DE REFERENCIA": 0
    },
    "Mujeres": {
      "0": 4,
      "1": 0,
      "12": 1,
      "124": 0,
      "13": 0,
      "14": 1,
      "15": 3,
      "16": 2,
      "17": 2,
      "18": 6,
      "19": 3,
      "2": 0,
      "20": 2,
      "21": 5,
      "22": 7,
      "23": 2,
      "24": 5,
      "25": 3,
      "26": 3,
      "27": 3,
      "28": 5,
      "29": 2,
      "3": 0,
      "30": 2,
      "31": 4,
      "32": 4,
      "33": 2,
      "34": 0,
      "35": 1,
      "36": 2,
      "37": 0,
      "38": 1,
      "39": 2,
      "40": 1,
      "41": 1,
      "42": 0,
      "43": 2,
      "44": 1,
      "45": 3,
      "46": 0,
      "47": 0,
      "48": 1,
      "49": 0,
      "50": 1,
      "51": 0,
      "52": 1,
      "53": 0,
      "54": 2,
      "55": 2,
      "56": 0,
      "57": 0,
      "58": 0,
      "59": 0,
      "60": 2,
      "61": 2,
      "62": 1,
      "63": 0,
      "64": 0,
      "65": 0,
      "66": 1,
      "67": 0,
      "68": 0,
      "70": 0,
      "71": 1,
      "72": 0,
      "73": 0,
      "74": 0,
      "75": 0,
      "76": 0,
      "77": 0,
      "78": 0,
      "79": 1,
      "80": 1,
      "81": 0,
      "82": 1,
      "83": 0,
      "84": 0,
      "85": 0,
      "86": 1,
      "87": 0,
      "89": 0,
      "93": 0,
      "SIN EDAD DE REFERENCIA": 2
    }
  },
  "por_nacionalidad": {
    "Hombres": {
      "COLOMBIANA": 1,
      "HONDUREÑA": 1,
      "MEXICANA": 534,
      "SE DESCONOCE": 100
    },
    "Indeterminado": {
      "COLOMBIANA": 0,
      "HONDUREÑA": 0,
      "MEXICANA": 0,
      "SE DESCONOCE": 0
    },
    "Mujeres": {
      "COLOMBIANA": 0,
      "HONDUREÑA": 0,
      "MEXICANA": 83,
      "SE DESCONOCE": 22
    }
  },
  "parametros": {
    "titulo": "PERSONAS LOCALIZADAS SIN VIDA",
    "id_estatus_victima": "3",
    "fecha_inicio": "",
    "fecha_fin": "",
    "id_estado": "30",
    "id_municipio": "0",
    "mostrar_fecha_nula": "0",
    "id_colonia": "0",
    "id_nacionalidad": "0",
    "edad_inicio": "",
    "edad_fin": "",
    "mostrar_edad_nula": "0",
    "id_hipotesis": "",
    "id_medio_conocimiento": "",
    "id_circunstancia": "",
    "tiene_discapacidad": "",
    "id_tipo_discapacidad": "0",
    "id_etnia": "0",
    "id_lengua": "0",
    "id_religion": "",
    "es_migrante": "",
    "id_estatus_migratorio": "0",
    "es_lgbttti": "",
    "es_servidor_publico": "",
    "es_defensor_dh": "",
    "es_periodista": "",
    "es_sindicalista": "",
    "es_ong": "",
    "id_hipotesis_no_localizacion": "0",
    "id_delito": "0"
  }
}