{
  "totales": {
    "PorcentajeDesaparecidos": "0.00",
    "PorcentajeLocalizados": "100.00",
    "PorcentajeLocalizadosCV": "88.60",
    "PorcentajeLocalizadosSV": "11.40",
    "PorcentajeSoloDesaparecidos": "0.00",
    "PorcentajeSoloNoLocalizados": "0.00",
    "TotalDesaparecidos": "00",
    "TotalGlobal": "1517",
    "TotalLocalizados": "1517",
    "TotalLocalizadosCV": "1344",
    "TotalLocalizadosSV": "173",
    "TotalSoloDesaparecidos": "00",
    "TotalSoloNoLocalizados": "00"
  },
  "espacial": {
    "Hombres": {
      "COMONDÚ": 35,
      "LA PAZ": 379,
      "LORETO": 16,
      "LOS CABOS": 318,
      "MULEGÉ": 30,
      "SE DESCONOCE": 1,
      "SIN MUNICIPIO DE REFERENCIA": 52
    },
    "Indeterminado": {
      "COMONDÚ": 0,
      "LA PAZ": 1,
      "LORETO": 0,
      "LOS CABOS": 0,
      "MULEGÉ": 0,
      "SE DESCONOCE": 0,
      "SIN MUNICIPIO DE REFERENCIA": 0
    },
    "Mujeres": {
      "COMONDÚ": 27,
      "LA PAZ": 320,
      "LORETO": 9,
      "LOS CABOS": 282,
      "MULEGÉ": 20,
      "SE DESCONOCE": 0,
      "SIN MUNICIPIO DE REFERENCIA": 27
    }
  },
  "anual": {
    "Hombre": {
      "1.CIFRA SIN  AÑO DE REFERENCIA": 39,
      "1996": 1,
      "2003": 0,
      "2010": 1,
      "2011": 1,
      "2012": 2,
      "2013": 7,
      "2014": 1,
      "2015": 1,
      "2016": 3,
      "2017": 7,
      "2018": 10,
      "2019": 20,
      "2020": 89,
      "2021": 120,
      "2022": 193,
      "2023": 245,
      "2024": 91
    },
    "Indeterminado": {
      "1.CIFRA SIN  AÑO DE REFERENCIA": 0,
      "1996": 0,
      "2003": 0,
      "2010": 0,
      "2011": 0,
      "2012": 0,
      "2013": 0,
      "2014": 0,
      "2015": 0,
      "2016": 1,
      "2017": 0,
      "2018": 0,
      "2019": 0,
      "2020": 0,
      "2021": 0,
      "2022": 0,
      "2023": 0,
      "2024": 0
    },
    "Mujer": {
      "1.CIFRA SIN  AÑO DE REFERENCIA": 19,
      "1996": 0,
      "2003": 1,
      "2010": 0,
      "2011": 1,
      "2012": 0,
      "2013": 8,
      "2014": 0,
      "2015": 0,
      "2016": 2,
      "2017": 1,
      "2018": 7,
      "2019": 5,
      "2020": 61,
      "2021": 106,
      "2022": 160,
      "2023": 237,
      "2024": 77
    }
  },
  "mensual_ultimo_anio": {
    "Hombre": {
      "2023-AGOSTO": 23,
      "2023-DICIEMBRE": 17,
      "2023-NOVIEMBRE": 20,
      "2023-OCTUBRE": 16,
      "2023-SEPTIEMBRE": 18,
      "2024-ABRIL": 11,
      "2024-ENERO": 26,
      "2024-FEBRERO": 13,
      "2024-JULIO": 4,
      "2024-JUNIO": 12,
      "2024-MARZO": 14,
      "2024-MAYO": 11
    },
    "Indeterminado": {
      "2023-AGOSTO": 0,
      "2023-DICIEMBRE": 0,
      "2023-NOVIEMBRE": 0,
      "2023-OCTUBRE": 0,
      "2023-SEPTIEMBRE": 0,
      "2024-ABRIL": 0,
      "2024-ENERO": 0,
      "2024-FEBRERO": 0,
      "2024-JULIO": 0,
      "2024-JUNIO": 0,
      "2024-MARZO": 0,
      "2024-MAYO": 0
    },
    "Mujer": {
      "2023-AGOSTO": 29,
      "2023-DICIEMBRE": 9,
      "2023-NOVIEMBRE": 17,
      "2023-OCTUBRE": 22,
      "2023-SEPTIEMBRE": 23,
      "2024-ABRIL": 12,
      "2024-ENERO": 8,
      "2024-FEBRERO": 10,
      "2024-JULIO": 3,
      "2024-JUNIO": 13,
      "2024-MARZO": 19,
      "2024-MAYO": 12
    }
  },
  "por_edad": {
    "Hombres": {
      "0": 2,
      "1": 2,
      "10": 5,
      "11": 5,
      "12": 6,
      "13": 15,
      "14": 22,
      "15": 20,
      "16": 26,
      "17": 24,
      "18": 9,
      "19": 11,
      "2": 1,
      "20": 14,
      "21": 19,
      "22": 27,
      "23": 17,
      "24": 21,
      "25": 15,
      "26": 37,
      "27": 25,
      "28": 23,
      "29": 17,
      "30": 20,
      "31": 25,
      "32": 17,
      "33": 13,
      "34": 16,
      "35": 14,
      "36": 15,
      "37": 15,
      "38": 19,
      "39": 17,
      "4": 3,
      "40": 15,
      "41": 8,
      "42": 19,
      "43": 11,
      "44": 14,
      "45": 14,
      "46": 19,
      "47": 10,
      "48": 13,
      "49": 7,
      "50": 7,
      "51": 10,
      "52": 8,
      "53": 8,
      "54": 7,
      "55": 4,
      "56": 5,
      "57": 8,
      "58": 7,
      "59": 1,
      "6": 3,
      "60": 5,
      "61": 4,
      "62": 5,
      "63": 5,
      "64": 3,
      "65": 2,
      "66": 3,
      "68": 2,
      "69": 1,
      "7": 1,
      "70": 1,
      "71": 4,
      "72": 2,
      "73": 3,
      "74": 2,
      "75": 2,
      "76": 2,
      "77": 3,
      "78": 0,
      "79": 2,
      "8": 1,
      "80": 4,
      "81": 1,
      "83": 1,
      "85": 1,
      "86": 1,
      "87": 4,
      "9": 2,
      "91": 1,
      "93": 1,
      "96": 0,
      "98": 1,
      "SIN EDAD DE REFERENCIA": 26
    },
    "Indeterminado": {
      "0": 0,
      "1": 0,
      "10": 0,
      "11": 0,
      "12": 0,
      "13": 0,
      "14": 0,
      "15": 0,
      "16": 0,
      "17": 0,
      "18": 0,
      "19": 0,
      "2": 0,
      "20": 1,
      "21": 0,
      "22": 0,
      "23": 0,
      "24": 0,
      "25": 0,
      "26": 0,
      "27": 0,
      "28": 0,
      "29": 0,
      "30": 0,
      "31": 0,
      "32": 0,
      "33": 0,
      "34": 0,
      "35": 0,
      "36": 0,
      "37": 0,
      "38": 0,
      "39": 0,
      "4": 0,
      "40": 0,
      "41": 0,
      "42": 0,
      "43": 0,
      "44": 0,
      "45": 0,
      "46": 0,
      "47": 0,
      "48": 0,
      "49": 0,
      "50": 0,
      "51": 0,
      "52": 0,
      "53": 0,
      "54": 0,
      "55": 0,
      "56": 0,
      "57": 0,
      "58": 0,
      "59": 0,
      "6": 0,
      "60": 0,
      "61": 0,
      "62": 0,
      "63": 0,
      "64": 0,
      "65": 0,
      "66": 0,
      "68": 0,
      "69": 0,
      "7": 0,
      "70": 0,
      "71": 0,
      "72": 0,
      "73": 0,
      "74": 0,
      "75": 0,
      "76": 0,
      "77": 0,
      "78": 0,
      "79": 0,
      "8": 0,
      "80": 0,
      "81": 0,
      "83": 0,
      "85": 0,
      "86": 0,
      "87": 0,
      "9": 0,
      "91": 0,
      "93": 0,
      "96": 0,
      "98": 0,
      "SIN EDAD DE REFERENCIA": 0
    },
    "Mujeres": {
      "0": 7,
      "1": 1,
      "10": 2,
      "11": 9,
      "12": 20,
      "13": 48,
      "14": 62,
      "15": 77,
      "16": 69,
      "17": 50,
      "18": 25,
      "19": 16,
      "2": 0,
      "20": 12,
      "21": 13,
      "22": 16,
      "23": 14,
      "24": 10,
      "25": 7,
      "26": 7,
      "27": 13,
      "28": 16,
      "29": 12,
      "30": 8,
      "31": 9,
      "32": 13,
      "33": 18,
      "34": 10,
      "35": 3,
      "36": 11,
      "37": 5,
      "38": 10,
      "39": 6,
      "4": 1,
      "40": 7,
      "41": 4,
      "42": 6,
      "43": 3,
      "44": 3,
      "45": 4,
      "46": 6,
      "47": 2,
      "48": 0,
      "49": 4,
      "50": 0,
      "51": 0,
      "52": 4,
      "53": 1,
      "54": 0,
      "55": 2,
      "56": 1,
      "57": 4,
      "58": 0,
      "59": 0,
      "6": 1,
      "60": 2,
      "61": 1,
      "62": 0,
      "63": 0,
      "64": 0,
      "65": 1,
      "66": 2,
      "68": 0,
      "69": 0,
      "7": 1,
      "70": 0,
      "71": 0,
      "72": 2,
      "73": 0,
      "74": 0,
      "75": 0,
      "76": 0,
      "77": 0,
      "78": 1,
      "79": 0,
      "8": 2,
      "80": 0,
      "81": 0,
      "83": 0,
      "85": 0,
      "86": 0,
      "87": 0,
      "9": 1,
      "91": 0,
      "93": 0,
      "96": 1,
      "98": 0,
      "SIN EDAD DE REFERENCIA": 19
    }
  },
  "por_nacionalidad": {
    "Hombres": {
      "ARGENTINA": 1,
      "CANADIENSE": 4,
      "COLOMBIANA": 1,
      "ESTADOUNIDENSE": 15,
      "INGLESA": 1,
      "MEXICANA": 809,
      "POLACA": 0,
      "SE DESCONOCE": 0,
      "SIN NACIONALIDAD DE REFERENCIA": 0
    },
    "Indeterminado": {
      "ARGENTINA": 0,
      "CANADIENSE": 0,
      "COLOMBIANA": 0,
      "ESTADOUNIDENSE": 0,
      "INGLESA": 0,
      "MEXICANA": 1,
      "POLACA": 0,
      "SE DESCONOCE": 0,
      "SIN NACIONALIDAD DE REFERENCIA": 0
    },
    "Mujeres": {
      "ARGENTINA": 0,
      "CANADIENSE": 0,
      "COLOMBIANA": 1,
      "ESTADOUNIDENSE": 3,
      "INGLESA": 0,
      "MEXICANA": 677,
      "POLACA": 1,
      "SE DESCONOCE": 2,
      "SIN NACIONALIDAD DE REFERENCIA": 1
    }
  },
  "parametros": {
    "titulo": "PERSONAS LOCALIZADAS",
    "id_estatus_victima": "6",
    "fecha_inicio": "",
    "fecha_fin": "",
    "id_estado": "3",
    "id_municipio": "0",
    "mostrar_fecha_nula": "0",
    "id_colonia": "0",
    "id_nacionalidad": "0",
    "edad_inicio": "",
    "edad_fin": "",
    "mostrar_edad_nula": "0",
    "id_hipotesis": "",
    "id_medio_conocimiento": "",
    "id_circunstancia": "",
    "tiene_discapacidad": "",
    "id_tipo_discapacidad": "0",
    "id_etnia": "0",
    "id_lengua": "0",
    "id_religion": "",
    "es_migrante": "",
    "id_estatus_migratorio": "0",
    "es_lgbttti": "",
    "es_servidor_publico": "",
    "es_defensor_dh": "",
    "es_periodista": "",
    "es_sindicalista": "",
    "es_ong": "",
    "id_hipotesis_no_localizacion": "0",
    "id_delito": "0"
  }
}